[
  {
    "#": "115",
    "DATE": "2026-01-25",
    "TRADING CODE": "FAMILYTEX",
    "LTP*": "1.1",
    "HIGH": "1.2",
    "LOW": "1.1",
    "OPENP*": "1.2",
    "CLOSEP*": "1.1",
    "YCP": "1.2",
    "TRADE": "42",
    "VALUE (mn)": "0.12",
    "VOLUME": "103223"
  },
  {
    "#": "114",
    "DATE": "2026-01-26",
    "TRADING CODE": "FAMILYTEX",
    "LTP*": "1.2",
    "HIGH": "1.2",
    "LOW": "1.1",
    "OPENP*": "1.1",
    "CLOSEP*": "1.1",
    "YCP": "1.1",
    "TRADE": "50",
    "VALUE (mn)": "0.113",
    "VOLUME": "97530"
  },
  {
    "#": "113",
    "DATE": "2026-01-27",
    "TRADING CODE": "FAMILYTEX",
    "LTP*": "1.2",
    "HIGH": "1.2",
    "LOW": "1.1",
    "OPENP*": "1.2",
    "CLOSEP*": "1.2",
    "YCP": "1.1",
    "TRADE": "53",
    "VALUE (mn)": "0.134",
    "VOLUME": "112993"
  },
  {
    "#": "112",
    "DATE": "2026-01-28",
    "TRADING CODE": "FAMILYTEX",
    "LTP*": "1.2",
    "HIGH": "1.3",
    "LOW": "1.1",
    "OPENP*": "1.2",
    "CLOSEP*": "1.1",
    "YCP": "1.2",
    "TRADE": "117",
    "VALUE (mn)": "0.447",
    "VOLUME": "374677"
  },
  {
    "#": "111",
    "DATE": "2026-01-29",
    "TRADING CODE": "FAMILYTEX",
    "LTP*": "1.2",
    "HIGH": "1.2",
    "LOW": "1.1",
    "OPENP*": "1.2",
    "CLOSEP*": "1.2",
    "YCP": "1.1",
    "TRADE": "51",
    "VALUE (mn)": "0.234",
    "VOLUME": "196154"
  },
  {
    "#": "110",
    "DATE": "2026-02-01",
    "TRADING CODE": "FAMILYTEX",
    "LTP*": "1.2",
    "HIGH": "1.3",
    "LOW": "1.1",
    "OPENP*": "1.2",
    "CLOSEP*": "1.2",
    "YCP": "1.2",
    "TRADE": "89",
    "VALUE (mn)": "0.173",
    "VOLUME": "147364"
  },
  {
    "#": "109",
    "DATE": "2026-02-02",
    "TRADING CODE": "FAMILYTEX",
    "LTP*": "1.2",
    "HIGH": "1.3",
    "LOW": "1.1",
    "OPENP*": "1.2",
    "CLOSEP*": "1.2",
    "YCP": "1.2",
    "TRADE": "106",
    "VALUE (mn)": "0.783",
    "VOLUME": "643848"
  },
  {
    "#": "108",
    "DATE": "2026-02-03",
    "TRADING CODE": "FAMILYTEX",
    "LTP*": "1.2",
    "HIGH": "1.3",
    "LOW": "1.1",
    "OPENP*": "1.2",
    "CLOSEP*": "1.2",
    "YCP": "1.2",
    "TRADE": "100",
    "VALUE (mn)": "0.607",
    "VOLUME": "505957"
  },
  {
    "#": "107",
    "DATE": "2026-02-05",
    "TRADING CODE": "FAMILYTEX",
    "LTP*": "1.3",
    "HIGH": "1.3",
    "LOW": "1.2",
    "OPENP*": "1.2",
    "CLOSEP*": "1.3",
    "YCP": "1.2",
    "TRADE": "47",
    "VALUE (mn)": "0.178",
    "VOLUME": "141524"
  },
  {
    "#": "106",
    "DATE": "2026-02-08",
    "TRADING CODE": "FAMILYTEX",
    "LTP*": "1.3",
    "HIGH": "1.3",
    "LOW": "1.2",
    "OPENP*": "1.3",
    "CLOSEP*": "1.3",
    "YCP": "1.3",
    "TRADE": "62",
    "VALUE (mn)": "0.22",
    "VOLUME": "172054"
  },
  {
    "#": "105",
    "DATE": "2026-02-09",
    "TRADING CODE": "FAMILYTEX",
    "LTP*": "1.4",
    "HIGH": "1.4",
    "LOW": "1.2",
    "OPENP*": "1.3",
    "CLOSEP*": "1.4",
    "YCP": "1.3",
    "TRADE": "273",
    "VALUE (mn)": "2.71",
    "VOLUME": "2024174"
  },
  {
    "#": "104",
    "DATE": "2026-02-10",
    "TRADING CODE": "FAMILYTEX",
    "LTP*": "1.5",
    "HIGH": "1.5",
    "LOW": "1.4",
    "OPENP*": "1.5",
    "CLOSEP*": "1.5",
    "YCP": "1.4",
    "TRADE": "300",
    "VALUE (mn)": "2.318",
    "VOLUME": "1552546"
  },
  {
    "#": "103",
    "DATE": "2026-02-15",
    "TRADING CODE": "FAMILYTEX",
    "LTP*": "1.6",
    "HIGH": "1.6",
    "LOW": "1.6",
    "OPENP*": "1.6",
    "CLOSEP*": "1.6",
    "YCP": "1.5",
    "TRADE": "37",
    "VALUE (mn)": "0.321",
    "VOLUME": "200349"
  },
  {
    "#": "102",
    "DATE": "2026-02-16",
    "TRADING CODE": "FAMILYTEX",
    "LTP*": "1.7",
    "HIGH": "1.7",
    "LOW": "1.7",
    "OPENP*": "1.7",
    "CLOSEP*": "1.7",
    "YCP": "1.6",
    "TRADE": "59",
    "VALUE (mn)": "0.668",
    "VOLUME": "393211"
  },
  {
    "#": "101",
    "DATE": "2026-02-17",
    "TRADING CODE": "FAMILYTEX",
    "LTP*": "1.8",
    "HIGH": "1.8",
    "LOW": "1.8",
    "OPENP*": "1.8",
    "CLOSEP*": "1.8",
    "YCP": "1.7",
    "TRADE": "119",
    "VALUE (mn)": "2.667",
    "VOLUME": "1481658"
  },
  {
    "#": "100",
    "DATE": "2026-02-18",
    "TRADING CODE": "FAMILYTEX",
    "LTP*": "1.9",
    "HIGH": "1.9",
    "LOW": "1.9",
    "OPENP*": "1.9",
    "CLOSEP*": "1.9",
    "YCP": "1.8",
    "TRADE": "125",
    "VALUE (mn)": "1.813",
    "VOLUME": "954088"
  },
  {
    "#": "99",
    "DATE": "2026-02-19",
    "TRADING CODE": "FAMILYTEX",
    "LTP*": "1.8",
    "HIGH": "2",
    "LOW": "1.8",
    "OPENP*": "2",
    "CLOSEP*": "1.8",
    "YCP": "1.9",
    "TRADE": "377",
    "VALUE (mn)": "8.569",
    "VOLUME": "4420524"
  },
  {
    "#": "98",
    "DATE": "2026-02-22",
    "TRADING CODE": "FAMILYTEX",
    "LTP*": "1.7",
    "HIGH": "1.7",
    "LOW": "1.7",
    "OPENP*": "1.7",
    "CLOSEP*": "1.7",
    "YCP": "1.8",
    "TRADE": "91",
    "VALUE (mn)": "0.689",
    "VOLUME": "405412"
  },
  {
    "#": "97",
    "DATE": "2026-02-23",
    "TRADING CODE": "FAMILYTEX",
    "LTP*": "1.8",
    "HIGH": "1.8",
    "LOW": "1.6",
    "OPENP*": "1.6",
    "CLOSEP*": "1.8",
    "YCP": "1.7",
    "TRADE": "282",
    "VALUE (mn)": "5.62",
    "VOLUME": "3201556"
  },
  {
    "#": "96",
    "DATE": "2026-02-24",
    "TRADING CODE": "FAMILYTEX",
    "LTP*": "1.9",
    "HIGH": "1.9",
    "LOW": "1.8",
    "OPENP*": "1.9",
    "CLOSEP*": "1.9",
    "YCP": "1.8",
    "TRADE": "265",
    "VALUE (mn)": "3.994",
    "VOLUME": "2102374"
  },
  {
    "#": "95",
    "DATE": "2026-02-25",
    "TRADING CODE": "FAMILYTEX",
    "LTP*": "2",
    "HIGH": "2",
    "LOW": "1.9",
    "OPENP*": "2",
    "CLOSEP*": "2",
    "YCP": "1.9",
    "TRADE": "488",
    "VALUE (mn)": "9.387",
    "VOLUME": "4693587"
  },
  {
    "#": "94",
    "DATE": "2026-02-26",
    "TRADING CODE": "FAMILYTEX",
    "LTP*": "2.2",
    "HIGH": "2.2",
    "LOW": "2",
    "OPENP*": "2",
    "CLOSEP*": "2.2",
    "YCP": "2",
    "TRADE": "532",
    "VALUE (mn)": "10.495",
    "VOLUME": "4813328"
  },
  {
    "#": "93",
    "DATE": "2026-03-01",
    "TRADING CODE": "FAMILYTEX",
    "LTP*": "2.4",
    "HIGH": "2.4",
    "LOW": "2",
    "OPENP*": "2.1",
    "CLOSEP*": "2.4",
    "YCP": "2.2",
    "TRADE": "724",
    "VALUE (mn)": "14.608",
    "VOLUME": "6416077"
  },
  {
    "#": "92",
    "DATE": "2026-03-02",
    "TRADING CODE": "FAMILYTEX",
    "LTP*": "2.6",
    "HIGH": "2.6",
    "LOW": "2.5",
    "OPENP*": "2.6",
    "CLOSEP*": "2.6",
    "YCP": "2.4",
    "TRADE": "160",
    "VALUE (mn)": "3.975",
    "VOLUME": "1550881"
  },
  {
    "#": "91",
    "DATE": "2026-03-03",
    "TRADING CODE": "FAMILYTEX",
    "LTP*": "2.8",
    "HIGH": "2.8",
    "LOW": "2.8",
    "OPENP*": "2.8",
    "CLOSEP*": "2.8",
    "YCP": "2.6",
    "TRADE": "214",
    "VALUE (mn)": "4.014",
    "VOLUME": "1433433"
  },
  {
    "#": "90",
    "DATE": "2026-03-04",
    "TRADING CODE": "FAMILYTEX",
    "LTP*": "3",
    "HIGH": "3",
    "LOW": "3",
    "OPENP*": "3",
    "CLOSEP*": "3",
    "YCP": "2.8",
    "TRADE": "146",
    "VALUE (mn)": "2.504",
    "VOLUME": "834783"
  },
  {
    "#": "89",
    "DATE": "2026-03-05",
    "TRADING CODE": "FAMILYTEX",
    "LTP*": "2.9",
    "HIGH": "3.3",
    "LOW": "2.8",
    "OPENP*": "3.3",
    "CLOSEP*": "2.9",
    "YCP": "3",
    "TRADE": "1676",
    "VALUE (mn)": "42.881",
    "VOLUME": "13646358"
  },
  {
    "#": "88",
    "DATE": "2026-03-08",
    "TRADING CODE": "FAMILYTEX",
    "LTP*": "2.7",
    "HIGH": "3",
    "LOW": "2.7",
    "OPENP*": "3",
    "CLOSEP*": "2.7",
    "YCP": "2.9",
    "TRADE": "612",
    "VALUE (mn)": "14.62",
    "VOLUME": "5368936"
  },
  {
    "#": "87",
    "DATE": "2026-03-09",
    "TRADING CODE": "FAMILYTEX",
    "LTP*": "2.9",
    "HIGH": "2.9",
    "LOW": "2.5",
    "OPENP*": "2.6",
    "CLOSEP*": "2.9",
    "YCP": "2.7",
    "TRADE": "636",
    "VALUE (mn)": "17.025",
    "VOLUME": "6042379"
  },
  {
    "#": "86",
    "DATE": "2026-03-10",
    "TRADING CODE": "FAMILYTEX",
    "LTP*": "3.1",
    "HIGH": "3.1",
    "LOW": "3",
    "OPENP*": "3.1",
    "CLOSEP*": "3.1",
    "YCP": "2.9",
    "TRADE": "298",
    "VALUE (mn)": "8.567",
    "VOLUME": "2764995"
  },
  {
    "#": "85",
    "DATE": "2026-03-11",
    "TRADING CODE": "FAMILYTEX",
    "LTP*": "3.4",
    "HIGH": "3.4",
    "LOW": "3.2",
    "OPENP*": "3.4",
    "CLOSEP*": "3.4",
    "YCP": "3.1",
    "TRADE": "1022",
    "VALUE (mn)": "27.839",
    "VOLUME": "8249207"
  },
  {
    "#": "84",
    "DATE": "2026-03-12",
    "TRADING CODE": "FAMILYTEX",
    "LTP*": "3.7",
    "HIGH": "3.7",
    "LOW": "3.4",
    "OPENP*": "3.7",
    "CLOSEP*": "3.7",
    "YCP": "3.4",
    "TRADE": "1655",
    "VALUE (mn)": "42.31",
    "VOLUME": "11649908"
  },
  {
    "#": "83",
    "DATE": "2026-03-15",
    "TRADING CODE": "FAMILYTEX",
    "LTP*": "4",
    "HIGH": "4",
    "LOW": "3.8",
    "OPENP*": "3.9",
    "CLOSEP*": "4",
    "YCP": "3.7",
    "TRADE": "354",
    "VALUE (mn)": "11.536",
    "VOLUME": "2895992"
  },
  {
    "#": "82",
    "DATE": "2026-03-16",
    "TRADING CODE": "FAMILYTEX",
    "LTP*": "4.3",
    "HIGH": "4.4",
    "LOW": "4",
    "OPENP*": "4.4",
    "CLOSEP*": "4.3",
    "YCP": "4",
    "TRADE": "1715",
    "VALUE (mn)": "54.511",
    "VOLUME": "12606096"
  },
  {
    "#": "81",
    "DATE": "2026-03-24",
    "TRADING CODE": "FAMILYTEX",
    "LTP*": "4.1",
    "HIGH": "4.6",
    "LOW": "4",
    "OPENP*": "4.5",
    "CLOSEP*": "4.1",
    "YCP": "4.3",
    "TRADE": "1365",
    "VALUE (mn)": "35.192",
    "VOLUME": "8418177"
  },
  {
    "#": "80",
    "DATE": "2026-03-25",
    "TRADING CODE": "FAMILYTEX",
    "LTP*": "3.8",
    "HIGH": "4.2",
    "LOW": "3.7",
    "OPENP*": "4.2",
    "CLOSEP*": "3.8",
    "YCP": "4.1",
    "TRADE": "1479",
    "VALUE (mn)": "37.418",
    "VOLUME": "9948925"
  },
  {
    "#": "79",
    "DATE": "2026-03-29",
    "TRADING CODE": "FAMILYTEX",
    "LTP*": "4",
    "HIGH": "4",
    "LOW": "3.7",
    "OPENP*": "3.8",
    "CLOSEP*": "4",
    "YCP": "3.8",
    "TRADE": "718",
    "VALUE (mn)": "13.409",
    "VOLUME": "3448441"
  },
  {
    "#": "78",
    "DATE": "2026-03-30",
    "TRADING CODE": "FAMILYTEX",
    "LTP*": "3.7",
    "HIGH": "4.1",
    "LOW": "3.6",
    "OPENP*": "4",
    "CLOSEP*": "3.7",
    "YCP": "4",
    "TRADE": "834",
    "VALUE (mn)": "19.675",
    "VOLUME": "5243562"
  },
  {
    "#": "77",
    "DATE": "2026-03-31",
    "TRADING CODE": "FAMILYTEX",
    "LTP*": "3.4",
    "HIGH": "3.7",
    "LOW": "3.4",
    "OPENP*": "3.7",
    "CLOSEP*": "3.4",
    "YCP": "3.7",
    "TRADE": "849",
    "VALUE (mn)": "14.54",
    "VOLUME": "4251649"
  },
  {
    "#": "76",
    "DATE": "2026-04-01",
    "TRADING CODE": "FAMILYTEX",
    "LTP*": "3.4",
    "HIGH": "3.6",
    "LOW": "3.1",
    "OPENP*": "3.4",
    "CLOSEP*": "3.4",
    "YCP": "3.4",
    "TRADE": "968",
    "VALUE (mn)": "16.42",
    "VOLUME": "5030346"
  },
  {
    "#": "75",
    "DATE": "2026-04-02",
    "TRADING CODE": "FAMILYTEX",
    "LTP*": "3.1",
    "HIGH": "3.5",
    "LOW": "3.1",
    "OPENP*": "3.5",
    "CLOSEP*": "3.1",
    "YCP": "3.4",
    "TRADE": "931",
    "VALUE (mn)": "13.716",
    "VOLUME": "4351391"
  },
  {
    "#": "74",
    "DATE": "2026-04-05",
    "TRADING CODE": "FAMILYTEX",
    "LTP*": "2.8",
    "HIGH": "3.2",
    "LOW": "2.8",
    "OPENP*": "3",
    "CLOSEP*": "2.8",
    "YCP": "3.1",
    "TRADE": "934",
    "VALUE (mn)": "13.71",
    "VOLUME": "4825976"
  },
  {
    "#": "73",
    "DATE": "2026-04-06",
    "TRADING CODE": "FAMILYTEX",
    "LTP*": "3",
    "HIGH": "3",
    "LOW": "2.6",
    "OPENP*": "2.6",
    "CLOSEP*": "3",
    "YCP": "2.8",
    "TRADE": "303",
    "VALUE (mn)": "4.858",
    "VOLUME": "1643970"
  },
  {
    "#": "72",
    "DATE": "2026-04-07",
    "TRADING CODE": "FAMILYTEX",
    "LTP*": "3.3",
    "HIGH": "3.3",
    "LOW": "3.2",
    "OPENP*": "3.2",
    "CLOSEP*": "3.3",
    "YCP": "3",
    "TRADE": "337",
    "VALUE (mn)": "7.704",
    "VOLUME": "2338301"
  },
  {
    "#": "71",
    "DATE": "2026-04-08",
    "TRADING CODE": "FAMILYTEX",
    "LTP*": "3.6",
    "HIGH": "3.6",
    "LOW": "3.4",
    "OPENP*": "3.6",
    "CLOSEP*": "3.6",
    "YCP": "3.3",
    "TRADE": "262",
    "VALUE (mn)": "5.177",
    "VOLUME": "1437937"
  },
  {
    "#": "70",
    "DATE": "2026-04-09",
    "TRADING CODE": "FAMILYTEX",
    "LTP*": "3.3",
    "HIGH": "3.9",
    "LOW": "3.3",
    "OPENP*": "3.9",
    "CLOSEP*": "3.3",
    "YCP": "3.6",
    "TRADE": "1184",
    "VALUE (mn)": "21.551",
    "VOLUME": "6280910"
  },
  {
    "#": "69",
    "DATE": "2026-04-12",
    "TRADING CODE": "FAMILYTEX",
    "LTP*": "3.2",
    "HIGH": "3.4",
    "LOW": "3.1",
    "OPENP*": "3.3",
    "CLOSEP*": "3.2",
    "YCP": "3.3",
    "TRADE": "519",
    "VALUE (mn)": "7.955",
    "VOLUME": "2460853"
  },
  {
    "#": "68",
    "DATE": "2026-04-13",
    "TRADING CODE": "FAMILYTEX",
    "LTP*": "3.3",
    "HIGH": "3.4",
    "LOW": "3.2",
    "OPENP*": "3.3",
    "CLOSEP*": "3.3",
    "YCP": "3.2",
    "TRADE": "258",
    "VALUE (mn)": "3.945",
    "VOLUME": "1201263"
  },
  {
    "#": "67",
    "DATE": "2026-04-15",
    "TRADING CODE": "FAMILYTEX",
    "LTP*": "3.3",
    "HIGH": "3.5",
    "LOW": "3.2",
    "OPENP*": "3.3",
    "CLOSEP*": "3.3",
    "YCP": "3.3",
    "TRADE": "377",
    "VALUE (mn)": "7.824",
    "VOLUME": "2349122"
  },
  {
    "#": "66",
    "DATE": "2026-04-16",
    "TRADING CODE": "FAMILYTEX",
    "LTP*": "3.1",
    "HIGH": "3.4",
    "LOW": "3.1",
    "OPENP*": "3.4",
    "CLOSEP*": "3.1",
    "YCP": "3.3",
    "TRADE": "374",
    "VALUE (mn)": "6.294",
    "VOLUME": "1953340"
  },
  {
    "#": "65",
    "DATE": "2026-04-19",
    "TRADING CODE": "FAMILYTEX",
    "LTP*": "3.1",
    "HIGH": "3.3",
    "LOW": "3.1",
    "OPENP*": "3.2",
    "CLOSEP*": "3.1",
    "YCP": "3.1",
    "TRADE": "254",
    "VALUE (mn)": "2.972",
    "VOLUME": "938748"
  },
  {
    "#": "64",
    "DATE": "2026-04-20",
    "TRADING CODE": "FAMILYTEX",
    "LTP*": "3",
    "HIGH": "3.2",
    "LOW": "3",
    "OPENP*": "3.2",
    "CLOSEP*": "3",
    "YCP": "3.1",
    "TRADE": "308",
    "VALUE (mn)": "3.527",
    "VOLUME": "1144392"
  },
  {
    "#": "63",
    "DATE": "2026-04-21",
    "TRADING CODE": "FAMILYTEX",
    "LTP*": "3.1",
    "HIGH": "3.2",
    "LOW": "3",
    "OPENP*": "3.1",
    "CLOSEP*": "3.1",
    "YCP": "3",
    "TRADE": "217",
    "VALUE (mn)": "3.337",
    "VOLUME": "1073630"
  },
  {
    "#": "62",
    "DATE": "2026-04-22",
    "TRADING CODE": "FAMILYTEX",
    "LTP*": "3.2",
    "HIGH": "3.3",
    "LOW": "3.1",
    "OPENP*": "3.2",
    "CLOSEP*": "3.2",
    "YCP": "3.1",
    "TRADE": "278",
    "VALUE (mn)": "5.14",
    "VOLUME": "1606359"
  },
  {
    "#": "61",
    "DATE": "2026-04-23",
    "TRADING CODE": "FAMILYTEX",
    "LTP*": "3.1",
    "HIGH": "3.2",
    "LOW": "3",
    "OPENP*": "3.2",
    "CLOSEP*": "3.1",
    "YCP": "3.2",
    "TRADE": "238",
    "VALUE (mn)": "3.363",
    "VOLUME": "1083003"
  },
  {
    "#": "60",
    "DATE": "2026-04-26",
    "TRADING CODE": "FAMILYTEX",
    "LTP*": "3",
    "HIGH": "3.2",
    "LOW": "2.9",
    "OPENP*": "3.1",
    "CLOSEP*": "2.9",
    "YCP": "3.1",
    "TRADE": "288",
    "VALUE (mn)": "3.345",
    "VOLUME": "1111605"
  },
  {
    "#": "59",
    "DATE": "2026-04-27",
    "TRADING CODE": "FAMILYTEX",
    "LTP*": "2.9",
    "HIGH": "3",
    "LOW": "2.8",
    "OPENP*": "3",
    "CLOSEP*": "2.9",
    "YCP": "2.9",
    "TRADE": "286",
    "VALUE (mn)": "3.062",
    "VOLUME": "1055287"
  },
  {
    "#": "58",
    "DATE": "2026-04-28",
    "TRADING CODE": "FAMILYTEX",
    "LTP*": "2.9",
    "HIGH": "2.9",
    "LOW": "2.8",
    "OPENP*": "2.9",
    "CLOSEP*": "2.9",
    "YCP": "2.9",
    "TRADE": "257",
    "VALUE (mn)": "3.359",
    "VOLUME": "1170495"
  },
  {
    "#": "57",
    "DATE": "2026-04-29",
    "TRADING CODE": "FAMILYTEX",
    "LTP*": "2.9",
    "HIGH": "3",
    "LOW": "2.8",
    "OPENP*": "2.8",
    "CLOSEP*": "2.9",
    "YCP": "2.9",
    "TRADE": "134",
    "VALUE (mn)": "2.599",
    "VOLUME": "894933"
  },
  {
    "#": "56",
    "DATE": "2026-04-30",
    "TRADING CODE": "FAMILYTEX",
    "LTP*": "3",
    "HIGH": "3",
    "LOW": "2.8",
    "OPENP*": "3",
    "CLOSEP*": "2.9",
    "YCP": "2.9",
    "TRADE": "178",
    "VALUE (mn)": "1.883",
    "VOLUME": "651125"
  },
  {
    "#": "55",
    "DATE": "2026-05-03",
    "TRADING CODE": "FAMILYTEX",
    "LTP*": "3",
    "HIGH": "3",
    "LOW": "2.9",
    "OPENP*": "3",
    "CLOSEP*": "2.9",
    "YCP": "2.9",
    "TRADE": "167",
    "VALUE (mn)": "2.748",
    "VOLUME": "937667"
  },
  {
    "#": "54",
    "DATE": "2026-05-04",
    "TRADING CODE": "FAMILYTEX",
    "LTP*": "2.9",
    "HIGH": "3",
    "LOW": "2.9",
    "OPENP*": "3",
    "CLOSEP*": "2.9",
    "YCP": "2.9",
    "TRADE": "149",
    "VALUE (mn)": "1.592",
    "VOLUME": "546225"
  },
  {
    "#": "53",
    "DATE": "2026-05-05",
    "TRADING CODE": "FAMILYTEX",
    "LTP*": "2.9",
    "HIGH": "3.1",
    "LOW": "2.9",
    "OPENP*": "3",
    "CLOSEP*": "2.9",
    "YCP": "2.9",
    "TRADE": "96",
    "VALUE (mn)": "1.315",
    "VOLUME": "450250"
  },
  {
    "#": "52",
    "DATE": "2026-05-06",
    "TRADING CODE": "FAMILYTEX",
    "LTP*": "2.9",
    "HIGH": "3",
    "LOW": "2.8",
    "OPENP*": "3",
    "CLOSEP*": "2.9",
    "YCP": "2.9",
    "TRADE": "201",
    "VALUE (mn)": "2.455",
    "VOLUME": "851465"
  },
  {
    "#": "51",
    "DATE": "2026-05-07",
    "TRADING CODE": "FAMILYTEX",
    "LTP*": "2.8",
    "HIGH": "3",
    "LOW": "2.8",
    "OPENP*": "2.9",
    "CLOSEP*": "2.8",
    "YCP": "2.9",
    "TRADE": "163",
    "VALUE (mn)": "2.851",
    "VOLUME": "1002757"
  },
  {
    "#": "50",
    "DATE": "2026-05-10",
    "TRADING CODE": "FAMILYTEX",
    "LTP*": "2.7",
    "HIGH": "2.9",
    "LOW": "2.7",
    "OPENP*": "2.8",
    "CLOSEP*": "2.7",
    "YCP": "2.8",
    "TRADE": "175",
    "VALUE (mn)": "1.573",
    "VOLUME": "569764"
  },
  {
    "#": "49",
    "DATE": "2026-05-11",
    "TRADING CODE": "FAMILYTEX",
    "LTP*": "2.6",
    "HIGH": "2.8",
    "LOW": "2.6",
    "OPENP*": "2.7",
    "CLOSEP*": "2.6",
    "YCP": "2.7",
    "TRADE": "318",
    "VALUE (mn)": "3.002",
    "VOLUME": "1130346"
  },
  {
    "#": "48",
    "DATE": "2026-05-12",
    "TRADING CODE": "FAMILYTEX",
    "LTP*": "2.6",
    "HIGH": "2.7",
    "LOW": "2.6",
    "OPENP*": "2.6",
    "CLOSEP*": "2.6",
    "YCP": "2.6",
    "TRADE": "133",
    "VALUE (mn)": "1.538",
    "VOLUME": "589007"
  },
  {
    "#": "47",
    "DATE": "2026-05-13",
    "TRADING CODE": "FAMILYTEX",
    "LTP*": "2.6",
    "HIGH": "2.7",
    "LOW": "2.6",
    "OPENP*": "2.6",
    "CLOSEP*": "2.6",
    "YCP": "2.6",
    "TRADE": "215",
    "VALUE (mn)": "2.017",
    "VOLUME": "773946"
  },
  {
    "#": "46",
    "DATE": "2026-05-14",
    "TRADING CODE": "FAMILYTEX",
    "LTP*": "2.8",
    "HIGH": "2.8",
    "LOW": "2.6",
    "OPENP*": "2.8",
    "CLOSEP*": "2.8",
    "YCP": "2.6",
    "TRADE": "291",
    "VALUE (mn)": "3.126",
    "VOLUME": "1127975"
  },
  {
    "#": "45",
    "DATE": "2026-05-17",
    "TRADING CODE": "FAMILYTEX",
    "LTP*": "2.8",
    "HIGH": "3",
    "LOW": "2.8",
    "OPENP*": "3",
    "CLOSEP*": "2.8",
    "YCP": "2.8",
    "TRADE": "277",
    "VALUE (mn)": "3.198",
    "VOLUME": "1129380"
  },
  {
    "#": "44",
    "DATE": "2026-05-18",
    "TRADING CODE": "FAMILYTEX",
    "LTP*": "2.7",
    "HIGH": "2.9",
    "LOW": "2.7",
    "OPENP*": "2.9",
    "CLOSEP*": "2.7",
    "YCP": "2.8",
    "TRADE": "161",
    "VALUE (mn)": "1.42",
    "VOLUME": "517029"
  },
  {
    "#": "43",
    "DATE": "2026-05-19",
    "TRADING CODE": "FAMILYTEX",
    "LTP*": "2.7",
    "HIGH": "2.8",
    "LOW": "2.6",
    "OPENP*": "2.7",
    "CLOSEP*": "2.7",
    "YCP": "2.7",
    "TRADE": "149",
    "VALUE (mn)": "1.257",
    "VOLUME": "465913"
  },
  {
    "#": "42",
    "DATE": "2026-05-20",
    "TRADING CODE": "FAMILYTEX",
    "LTP*": "2.9",
    "HIGH": "2.9",
    "LOW": "2.8",
    "OPENP*": "2.8",
    "CLOSEP*": "2.9",
    "YCP": "2.7",
    "TRADE": "249",
    "VALUE (mn)": "4.591",
    "VOLUME": "1596778"
  },
  {
    "#": "41",
    "DATE": "2026-05-21",
    "TRADING CODE": "FAMILYTEX",
    "LTP*": "3",
    "HIGH": "3.1",
    "LOW": "2.9",
    "OPENP*": "3.1",
    "CLOSEP*": "3",
    "YCP": "2.9",
    "TRADE": "412",
    "VALUE (mn)": "6.326",
    "VOLUME": "2101789"
  },
  {
    "#": "40",
    "DATE": "2026-05-23",
    "TRADING CODE": "FAMILYTEX",
    "LTP*": "2.9",
    "HIGH": "3.1",
    "LOW": "2.8",
    "OPENP*": "3",
    "CLOSEP*": "2.9",
    "YCP": "3",
    "TRADE": "259",
    "VALUE (mn)": "3.048",
    "VOLUME": "1062440"
  },
  {
    "#": "39",
    "DATE": "2026-05-24",
    "TRADING CODE": "FAMILYTEX",
    "LTP*": "3",
    "HIGH": "3.1",
    "LOW": "2.8",
    "OPENP*": "2.9",
    "CLOSEP*": "2.9",
    "YCP": "2.9",
    "TRADE": "330",
    "VALUE (mn)": "6.117",
    "VOLUME": "2076993"
  },
  {
    "#": "38",
    "DATE": "2026-06-01",
    "TRADING CODE": "FAMILYTEX",
    "LTP*": "2.9",
    "HIGH": "3",
    "LOW": "2.8",
    "OPENP*": "2.9",
    "CLOSEP*": "2.8",
    "YCP": "2.9",
    "TRADE": "125",
    "VALUE (mn)": "1.82",
    "VOLUME": "632854"
  },
  {
    "#": "37",
    "DATE": "2026-06-02",
    "TRADING CODE": "FAMILYTEX",
    "LTP*": "2.8",
    "HIGH": "2.9",
    "LOW": "2.7",
    "OPENP*": "2.9",
    "CLOSEP*": "2.8",
    "YCP": "2.8",
    "TRADE": "277",
    "VALUE (mn)": "3.697",
    "VOLUME": "1318560"
  },
  {
    "#": "36",
    "DATE": "2026-06-03",
    "TRADING CODE": "FAMILYTEX",
    "LTP*": "2.9",
    "HIGH": "3",
    "LOW": "2.8",
    "OPENP*": "2.9",
    "CLOSEP*": "2.9",
    "YCP": "2.8",
    "TRADE": "303",
    "VALUE (mn)": "3.831",
    "VOLUME": "1325985"
  },
  {
    "#": "35",
    "DATE": "2026-06-04",
    "TRADING CODE": "FAMILYTEX",
    "LTP*": "2.9",
    "HIGH": "3",
    "LOW": "2.8",
    "OPENP*": "2.9",
    "CLOSEP*": "2.8",
    "YCP": "2.9",
    "TRADE": "242",
    "VALUE (mn)": "3.483",
    "VOLUME": "1218788"
  },
  {
    "#": "34",
    "DATE": "2026-06-07",
    "TRADING CODE": "FAMILYTEX",
    "LTP*": "2.8",
    "HIGH": "3",
    "LOW": "2.8",
    "OPENP*": "3",
    "CLOSEP*": "2.8",
    "YCP": "2.8",
    "TRADE": "154",
    "VALUE (mn)": "2.406",
    "VOLUME": "840669"
  },
  {
    "#": "33",
    "DATE": "2026-06-08",
    "TRADING CODE": "FAMILYTEX",
    "LTP*": "2.8",
    "HIGH": "2.9",
    "LOW": "2.7",
    "OPENP*": "2.9",
    "CLOSEP*": "2.8",
    "YCP": "2.8",
    "TRADE": "233",
    "VALUE (mn)": "3.161",
    "VOLUME": "1130084"
  },
  {
    "#": "32",
    "DATE": "2026-06-09",
    "TRADING CODE": "FAMILYTEX",
    "LTP*": "2.8",
    "HIGH": "2.9",
    "LOW": "2.7",
    "OPENP*": "2.9",
    "CLOSEP*": "2.8",
    "YCP": "2.8",
    "TRADE": "165",
    "VALUE (mn)": "1.499",
    "VOLUME": "540551"
  },
  {
    "#": "31",
    "DATE": "2026-06-10",
    "TRADING CODE": "FAMILYTEX",
    "LTP*": "2.8",
    "HIGH": "2.9",
    "LOW": "2.7",
    "OPENP*": "2.9",
    "CLOSEP*": "2.8",
    "YCP": "2.8",
    "TRADE": "207",
    "VALUE (mn)": "2.668",
    "VOLUME": "952544"
  },
  {
    "#": "30",
    "DATE": "2026-06-11",
    "TRADING CODE": "FAMILYTEX",
    "LTP*": "2.7",
    "HIGH": "2.9",
    "LOW": "2.7",
    "OPENP*": "2.8",
    "CLOSEP*": "2.7",
    "YCP": "2.8",
    "TRADE": "169",
    "VALUE (mn)": "2.114",
    "VOLUME": "768481"
  },
  {
    "#": "29",
    "DATE": "2026-06-14",
    "TRADING CODE": "FAMILYTEX",
    "LTP*": "2.8",
    "HIGH": "2.9",
    "LOW": "2.7",
    "OPENP*": "2.8",
    "CLOSEP*": "2.8",
    "YCP": "2.7",
    "TRADE": "265",
    "VALUE (mn)": "5.061",
    "VOLUME": "1801558"
  },
  {
    "#": "28",
    "DATE": "2026-06-15",
    "TRADING CODE": "FAMILYTEX",
    "LTP*": "2.8",
    "HIGH": "2.9",
    "LOW": "2.7",
    "OPENP*": "2.8",
    "CLOSEP*": "2.8",
    "YCP": "2.8",
    "TRADE": "173",
    "VALUE (mn)": "2.256",
    "VOLUME": "805692"
  },
  {
    "#": "27",
    "DATE": "2026-06-16",
    "TRADING CODE": "FAMILYTEX",
    "LTP*": "2.8",
    "HIGH": "2.9",
    "LOW": "2.7",
    "OPENP*": "2.8",
    "CLOSEP*": "2.8",
    "YCP": "2.8",
    "TRADE": "161",
    "VALUE (mn)": "1.588",
    "VOLUME": "568212"
  },
  {
    "#": "26",
    "DATE": "2026-06-17",
    "TRADING CODE": "FAMILYTEX",
    "LTP*": "2.8",
    "HIGH": "2.9",
    "LOW": "2.7",
    "OPENP*": "2.9",
    "CLOSEP*": "2.8",
    "YCP": "2.8",
    "TRADE": "240",
    "VALUE (mn)": "4.706",
    "VOLUME": "1684067"
  },
  {
    "#": "25",
    "DATE": "2026-06-18",
    "TRADING CODE": "FAMILYTEX",
    "LTP*": "2.8",
    "HIGH": "2.9",
    "LOW": "2.7",
    "OPENP*": "2.8",
    "CLOSEP*": "2.8",
    "YCP": "2.8",
    "TRADE": "203",
    "VALUE (mn)": "3.188",
    "VOLUME": "1143580"
  },
  {
    "#": "24",
    "DATE": "2026-06-21",
    "TRADING CODE": "FAMILYTEX",
    "LTP*": "2.8",
    "HIGH": "2.8",
    "LOW": "2.7",
    "OPENP*": "2.8",
    "CLOSEP*": "2.7",
    "YCP": "2.8",
    "TRADE": "117",
    "VALUE (mn)": "2.218",
    "VOLUME": "816035"
  },
  {
    "#": "23",
    "DATE": "2026-06-22",
    "TRADING CODE": "FAMILYTEX",
    "LTP*": "2.7",
    "HIGH": "2.8",
    "LOW": "2.7",
    "OPENP*": "2.7",
    "CLOSEP*": "2.7",
    "YCP": "2.7",
    "TRADE": "201",
    "VALUE (mn)": "2.434",
    "VOLUME": "900876"
  },
  {
    "#": "22",
    "DATE": "2026-06-23",
    "TRADING CODE": "FAMILYTEX",
    "LTP*": "2.7",
    "HIGH": "2.8",
    "LOW": "2.6",
    "OPENP*": "2.7",
    "CLOSEP*": "2.7",
    "YCP": "2.7",
    "TRADE": "192",
    "VALUE (mn)": "2.027",
    "VOLUME": "750837"
  },
  {
    "#": "21",
    "DATE": "2026-06-24",
    "TRADING CODE": "FAMILYTEX",
    "LTP*": "2.7",
    "HIGH": "2.7",
    "LOW": "2.6",
    "OPENP*": "2.7",
    "CLOSEP*": "2.7",
    "YCP": "2.7",
    "TRADE": "153",
    "VALUE (mn)": "1.315",
    "VOLUME": "493510"
  },
  {
    "#": "20",
    "DATE": "2026-06-25",
    "TRADING CODE": "FAMILYTEX",
    "LTP*": "2.6",
    "HIGH": "2.7",
    "LOW": "2.6",
    "OPENP*": "2.7",
    "CLOSEP*": "2.6",
    "YCP": "2.7",
    "TRADE": "150",
    "VALUE (mn)": "2.176",
    "VOLUME": "828067"
  },
  {
    "#": "19",
    "DATE": "2026-06-28",
    "TRADING CODE": "FAMILYTEX",
    "LTP*": "2.6",
    "HIGH": "2.7",
    "LOW": "2.6",
    "OPENP*": "2.7",
    "CLOSEP*": "2.6",
    "YCP": "2.6",
    "TRADE": "200",
    "VALUE (mn)": "2.605",
    "VOLUME": "995388"
  },
  {
    "#": "18",
    "DATE": "2026-06-29",
    "TRADING CODE": "FAMILYTEX",
    "LTP*": "2.5",
    "HIGH": "2.7",
    "LOW": "2.5",
    "OPENP*": "2.6",
    "CLOSEP*": "2.5",
    "YCP": "2.6",
    "TRADE": "340",
    "VALUE (mn)": "4.701",
    "VOLUME": "1847745"
  },
  {
    "#": "17",
    "DATE": "2026-06-30",
    "TRADING CODE": "FAMILYTEX",
    "LTP*": "2.6",
    "HIGH": "2.6",
    "LOW": "2.5",
    "OPENP*": "2.5",
    "CLOSEP*": "2.6",
    "YCP": "2.5",
    "TRADE": "220",
    "VALUE (mn)": "2.782",
    "VOLUME": "1087824"
  },
  {
    "#": "16",
    "DATE": "2026-07-02",
    "TRADING CODE": "FAMILYTEX",
    "LTP*": "2.6",
    "HIGH": "2.6",
    "LOW": "2.5",
    "OPENP*": "2.6",
    "CLOSEP*": "2.6",
    "YCP": "2.6",
    "TRADE": "179",
    "VALUE (mn)": "2.715",
    "VOLUME": "1070194"
  },
  {
    "#": "15",
    "DATE": "2026-07-05",
    "TRADING CODE": "FAMILYTEX",
    "LTP*": "2.4",
    "HIGH": "2.6",
    "LOW": "2.4",
    "OPENP*": "2.6",
    "CLOSEP*": "2.4",
    "YCP": "2.6",
    "TRADE": "479",
    "VALUE (mn)": "4.883",
    "VOLUME": "1998440"
  },
  {
    "#": "14",
    "DATE": "2026-07-06",
    "TRADING CODE": "FAMILYTEX",
    "LTP*": "2.4",
    "HIGH": "2.5",
    "LOW": "2.2",
    "OPENP*": "2.5",
    "CLOSEP*": "2.4",
    "YCP": "2.4",
    "TRADE": "422",
    "VALUE (mn)": "3.573",
    "VOLUME": "1524763"
  },
  {
    "#": "13",
    "DATE": "2026-07-07",
    "TRADING CODE": "FAMILYTEX",
    "LTP*": "2.5",
    "HIGH": "2.5",
    "LOW": "2.3",
    "OPENP*": "2.5",
    "CLOSEP*": "2.5",
    "YCP": "2.4",
    "TRADE": "112",
    "VALUE (mn)": "0.62",
    "VOLUME": "252944"
  },
  {
    "#": "12",
    "DATE": "2026-07-08",
    "TRADING CODE": "FAMILYTEX",
    "LTP*": "2.4",
    "HIGH": "2.5",
    "LOW": "2.4",
    "OPENP*": "2.5",
    "CLOSEP*": "2.4",
    "YCP": "2.5",
    "TRADE": "112",
    "VALUE (mn)": "0.745",
    "VOLUME": "308848"
  },
  {
    "#": "11",
    "DATE": "2026-07-09",
    "TRADING CODE": "FAMILYTEX",
    "LTP*": "2.5",
    "HIGH": "2.5",
    "LOW": "2.4",
    "OPENP*": "2.5",
    "CLOSEP*": "2.5",
    "YCP": "2.4",
    "TRADE": "180",
    "VALUE (mn)": "2.494",
    "VOLUME": "1030119"
  },
  {
    "#": "10",
    "DATE": "2026-07-12",
    "TRADING CODE": "FAMILYTEX",
    "LTP*": "2.3",
    "HIGH": "2.5",
    "LOW": "2.3",
    "OPENP*": "2.4",
    "CLOSEP*": "2.3",
    "YCP": "2.5",
    "TRADE": "379",
    "VALUE (mn)": "3.275",
    "VOLUME": "1416791"
  },
  {
    "#": "9",
    "DATE": "2026-07-13",
    "TRADING CODE": "FAMILYTEX",
    "LTP*": "2.3",
    "HIGH": "2.4",
    "LOW": "2.2",
    "OPENP*": "2.4",
    "CLOSEP*": "2.2",
    "YCP": "2.3",
    "TRADE": "331",
    "VALUE (mn)": "4.066",
    "VOLUME": "1768826"
  },
  {
    "#": "8",
    "DATE": "2026-07-14",
    "TRADING CODE": "FAMILYTEX",
    "LTP*": "2.4",
    "HIGH": "2.4",
    "LOW": "2.2",
    "OPENP*": "2.2",
    "CLOSEP*": "2.4",
    "YCP": "2.2",
    "TRADE": "276",
    "VALUE (mn)": "2.039",
    "VOLUME": "881095"
  },
  {
    "#": "7",
    "DATE": "2026-07-15",
    "TRADING CODE": "FAMILYTEX",
    "LTP*": "2.3",
    "HIGH": "2.4",
    "LOW": "2.3",
    "OPENP*": "2.4",
    "CLOSEP*": "2.3",
    "YCP": "2.4",
    "TRADE": "189",
    "VALUE (mn)": "1.589",
    "VOLUME": "687807"
  },
  {
    "#": "6",
    "DATE": "2026-07-16",
    "TRADING CODE": "FAMILYTEX",
    "LTP*": "2.3",
    "HIGH": "2.4",
    "LOW": "2.2",
    "OPENP*": "2.3",
    "CLOSEP*": "2.3",
    "YCP": "2.3",
    "TRADE": "206",
    "VALUE (mn)": "1.46",
    "VOLUME": "635529"
  },
  {
    "#": "5",
    "DATE": "2026-07-19",
    "TRADING CODE": "FAMILYTEX",
    "LTP*": "2.3",
    "HIGH": "2.4",
    "LOW": "2.3",
    "OPENP*": "2.3",
    "CLOSEP*": "2.3",
    "YCP": "2.3",
    "TRADE": "133",
    "VALUE (mn)": "1.475",
    "VOLUME": "638109"
  },
  {
    "#": "4",
    "DATE": "2026-07-20",
    "TRADING CODE": "FAMILYTEX",
    "LTP*": "2.3",
    "HIGH": "2.4",
    "LOW": "2.2",
    "OPENP*": "2.3",
    "CLOSEP*": "2.3",
    "YCP": "2.3",
    "TRADE": "166",
    "VALUE (mn)": "1.431",
    "VOLUME": "621690"
  },
  {
    "#": "3",
    "DATE": "2026-07-21",
    "TRADING CODE": "FAMILYTEX",
    "LTP*": "2.3",
    "HIGH": "2.4",
    "LOW": "2.2",
    "OPENP*": "2.3",
    "CLOSEP*": "2.3",
    "YCP": "2.3",
    "TRADE": "200",
    "VALUE (mn)": "2.413",
    "VOLUME": "1055942"
  },
  {
    "#": "2",
    "DATE": "2026-07-22",
    "TRADING CODE": "FAMILYTEX",
    "LTP*": "2.3",
    "HIGH": "2.4",
    "LOW": "2.2",
    "OPENP*": "2.3",
    "CLOSEP*": "2.3",
    "YCP": "2.3",
    "TRADE": "258",
    "VALUE (mn)": "4.66",
    "VOLUME": "2026598"
  },
  {
    "#": "1",
    "DATE": "2026-07-23",
    "TRADING CODE": "FAMILYTEX",
    "LTP*": "2.5",
    "HIGH": "2.5",
    "LOW": "2.3",
    "OPENP*": "2.3",
    "CLOSEP*": "2.5",
    "YCP": "2.3",
    "TRADE": "393",
    "VALUE (mn)": "6.793",
    "VOLUME": "2771866"
  }
]