[
  {
    "#": "74",
    "DATE": "2026-03-24",
    "TRADING CODE": "RINGSHINE",
    "LTP*": "4.1",
    "HIGH": "4.4",
    "LOW": "4.1",
    "OPENP*": "4.2",
    "CLOSEP*": "4.1",
    "YCP": "4.1",
    "TRADE": "456",
    "VALUE (mn)": "10.094",
    "VOLUME": "2384693"
  },
  {
    "#": "73",
    "DATE": "2026-03-25",
    "TRADING CODE": "RINGSHINE",
    "LTP*": "3.9",
    "HIGH": "4.1",
    "LOW": "3.7",
    "OPENP*": "4.1",
    "CLOSEP*": "3.9",
    "YCP": "4.1",
    "TRADE": "448",
    "VALUE (mn)": "11.03",
    "VOLUME": "2843319"
  },
  {
    "#": "72",
    "DATE": "2026-03-29",
    "TRADING CODE": "RINGSHINE",
    "LTP*": "4",
    "HIGH": "4",
    "LOW": "3.7",
    "OPENP*": "3.9",
    "CLOSEP*": "4",
    "YCP": "3.9",
    "TRADE": "325",
    "VALUE (mn)": "6.031",
    "VOLUME": "1577228"
  },
  {
    "#": "71",
    "DATE": "2026-03-30",
    "TRADING CODE": "RINGSHINE",
    "LTP*": "3.7",
    "HIGH": "4.1",
    "LOW": "3.7",
    "OPENP*": "4",
    "CLOSEP*": "3.7",
    "YCP": "4",
    "TRADE": "417",
    "VALUE (mn)": "9.94",
    "VOLUME": "2605895"
  },
  {
    "#": "70",
    "DATE": "2026-03-31",
    "TRADING CODE": "RINGSHINE",
    "LTP*": "3.5",
    "HIGH": "3.8",
    "LOW": "3.5",
    "OPENP*": "3.8",
    "CLOSEP*": "3.5",
    "YCP": "3.7",
    "TRADE": "386",
    "VALUE (mn)": "7.097",
    "VOLUME": "1986537"
  },
  {
    "#": "69",
    "DATE": "2026-04-01",
    "TRADING CODE": "RINGSHINE",
    "LTP*": "3.8",
    "HIGH": "3.8",
    "LOW": "3.5",
    "OPENP*": "3.6",
    "CLOSEP*": "3.8",
    "YCP": "3.5",
    "TRADE": "310",
    "VALUE (mn)": "4.226",
    "VOLUME": "1131313"
  },
  {
    "#": "68",
    "DATE": "2026-04-02",
    "TRADING CODE": "RINGSHINE",
    "LTP*": "3.6",
    "HIGH": "3.9",
    "LOW": "3.6",
    "OPENP*": "3.8",
    "CLOSEP*": "3.6",
    "YCP": "3.8",
    "TRADE": "224",
    "VALUE (mn)": "1.487",
    "VOLUME": "402710"
  },
  {
    "#": "67",
    "DATE": "2026-04-05",
    "TRADING CODE": "RINGSHINE",
    "LTP*": "3.3",
    "HIGH": "3.6",
    "LOW": "3.3",
    "OPENP*": "3.6",
    "CLOSEP*": "3.3",
    "YCP": "3.6",
    "TRADE": "272",
    "VALUE (mn)": "3.309",
    "VOLUME": "978136"
  },
  {
    "#": "66",
    "DATE": "2026-04-06",
    "TRADING CODE": "RINGSHINE",
    "LTP*": "3.5",
    "HIGH": "3.5",
    "LOW": "3.3",
    "OPENP*": "3.3",
    "CLOSEP*": "3.5",
    "YCP": "3.3",
    "TRADE": "114",
    "VALUE (mn)": "1.326",
    "VOLUME": "379747"
  },
  {
    "#": "65",
    "DATE": "2026-04-07",
    "TRADING CODE": "RINGSHINE",
    "LTP*": "3.6",
    "HIGH": "3.6",
    "LOW": "3.5",
    "OPENP*": "3.6",
    "CLOSEP*": "3.6",
    "YCP": "3.5",
    "TRADE": "178",
    "VALUE (mn)": "2.566",
    "VOLUME": "719524"
  },
  {
    "#": "64",
    "DATE": "2026-04-08",
    "TRADING CODE": "RINGSHINE",
    "LTP*": "3.8",
    "HIGH": "3.9",
    "LOW": "3.7",
    "OPENP*": "3.7",
    "CLOSEP*": "3.8",
    "YCP": "3.6",
    "TRADE": "381",
    "VALUE (mn)": "9.409",
    "VOLUME": "2477699"
  },
  {
    "#": "63",
    "DATE": "2026-04-09",
    "TRADING CODE": "RINGSHINE",
    "LTP*": "3.5",
    "HIGH": "3.9",
    "LOW": "3.5",
    "OPENP*": "3.9",
    "CLOSEP*": "3.5",
    "YCP": "3.8",
    "TRADE": "299",
    "VALUE (mn)": "3.413",
    "VOLUME": "941467"
  },
  {
    "#": "62",
    "DATE": "2026-04-12",
    "TRADING CODE": "RINGSHINE",
    "LTP*": "3.5",
    "HIGH": "3.7",
    "LOW": "3.5",
    "OPENP*": "3.7",
    "CLOSEP*": "3.5",
    "YCP": "3.5",
    "TRADE": "201",
    "VALUE (mn)": "2.038",
    "VOLUME": "574724"
  },
  {
    "#": "61",
    "DATE": "2026-04-13",
    "TRADING CODE": "RINGSHINE",
    "LTP*": "3.6",
    "HIGH": "3.7",
    "LOW": "3.5",
    "OPENP*": "3.7",
    "CLOSEP*": "3.6",
    "YCP": "3.5",
    "TRADE": "162",
    "VALUE (mn)": "2.246",
    "VOLUME": "618874"
  },
  {
    "#": "60",
    "DATE": "2026-04-15",
    "TRADING CODE": "RINGSHINE",
    "LTP*": "3.6",
    "HIGH": "3.7",
    "LOW": "3.5",
    "OPENP*": "3.6",
    "CLOSEP*": "3.6",
    "YCP": "3.6",
    "TRADE": "164",
    "VALUE (mn)": "1.97",
    "VOLUME": "548324"
  },
  {
    "#": "59",
    "DATE": "2026-04-16",
    "TRADING CODE": "RINGSHINE",
    "LTP*": "3.5",
    "HIGH": "3.7",
    "LOW": "3.5",
    "OPENP*": "3.6",
    "CLOSEP*": "3.5",
    "YCP": "3.6",
    "TRADE": "184",
    "VALUE (mn)": "3.151",
    "VOLUME": "891154"
  },
  {
    "#": "58",
    "DATE": "2026-04-19",
    "TRADING CODE": "RINGSHINE",
    "LTP*": "3.4",
    "HIGH": "3.6",
    "LOW": "3.4",
    "OPENP*": "3.6",
    "CLOSEP*": "3.4",
    "YCP": "3.5",
    "TRADE": "140",
    "VALUE (mn)": "1.597",
    "VOLUME": "460106"
  },
  {
    "#": "57",
    "DATE": "2026-04-20",
    "TRADING CODE": "RINGSHINE",
    "LTP*": "3.4",
    "HIGH": "3.5",
    "LOW": "3.4",
    "OPENP*": "3.5",
    "CLOSEP*": "3.4",
    "YCP": "3.4",
    "TRADE": "89",
    "VALUE (mn)": "1.145",
    "VOLUME": "334679"
  },
  {
    "#": "56",
    "DATE": "2026-04-21",
    "TRADING CODE": "RINGSHINE",
    "LTP*": "3.7",
    "HIGH": "3.7",
    "LOW": "3.5",
    "OPENP*": "3.5",
    "CLOSEP*": "3.7",
    "YCP": "3.4",
    "TRADE": "282",
    "VALUE (mn)": "6.429",
    "VOLUME": "1742426"
  },
  {
    "#": "55",
    "DATE": "2026-04-22",
    "TRADING CODE": "RINGSHINE",
    "LTP*": "4",
    "HIGH": "4",
    "LOW": "3.8",
    "OPENP*": "4",
    "CLOSEP*": "4",
    "YCP": "3.7",
    "TRADE": "310",
    "VALUE (mn)": "11.779",
    "VOLUME": "2952077"
  },
  {
    "#": "54",
    "DATE": "2026-04-23",
    "TRADING CODE": "RINGSHINE",
    "LTP*": "3.9",
    "HIGH": "4.4",
    "LOW": "3.9",
    "OPENP*": "4.3",
    "CLOSEP*": "3.9",
    "YCP": "4",
    "TRADE": "854",
    "VALUE (mn)": "18.327",
    "VOLUME": "4474267"
  },
  {
    "#": "53",
    "DATE": "2026-04-26",
    "TRADING CODE": "RINGSHINE",
    "LTP*": "3.8",
    "HIGH": "3.9",
    "LOW": "3.7",
    "OPENP*": "3.9",
    "CLOSEP*": "3.7",
    "YCP": "3.9",
    "TRADE": "315",
    "VALUE (mn)": "4.706",
    "VOLUME": "1258698"
  },
  {
    "#": "52",
    "DATE": "2026-04-27",
    "TRADING CODE": "RINGSHINE",
    "LTP*": "3.7",
    "HIGH": "3.8",
    "LOW": "3.5",
    "OPENP*": "3.7",
    "CLOSEP*": "3.7",
    "YCP": "3.7",
    "TRADE": "266",
    "VALUE (mn)": "6.036",
    "VOLUME": "1666497"
  },
  {
    "#": "51",
    "DATE": "2026-04-28",
    "TRADING CODE": "RINGSHINE",
    "LTP*": "3.6",
    "HIGH": "3.8",
    "LOW": "3.5",
    "OPENP*": "3.7",
    "CLOSEP*": "3.6",
    "YCP": "3.7",
    "TRADE": "264",
    "VALUE (mn)": "3.668",
    "VOLUME": "1010468"
  },
  {
    "#": "50",
    "DATE": "2026-04-29",
    "TRADING CODE": "RINGSHINE",
    "LTP*": "3.7",
    "HIGH": "3.7",
    "LOW": "3.5",
    "OPENP*": "3.7",
    "CLOSEP*": "3.7",
    "YCP": "3.6",
    "TRADE": "142",
    "VALUE (mn)": "2.14",
    "VOLUME": "588644"
  },
  {
    "#": "49",
    "DATE": "2026-04-30",
    "TRADING CODE": "RINGSHINE",
    "LTP*": "3.6",
    "HIGH": "3.7",
    "LOW": "3.6",
    "OPENP*": "3.7",
    "CLOSEP*": "3.6",
    "YCP": "3.7",
    "TRADE": "155",
    "VALUE (mn)": "1.794",
    "VOLUME": "496699"
  },
  {
    "#": "48",
    "DATE": "2026-05-03",
    "TRADING CODE": "RINGSHINE",
    "LTP*": "3.6",
    "HIGH": "3.7",
    "LOW": "3.6",
    "OPENP*": "3.7",
    "CLOSEP*": "3.6",
    "YCP": "3.6",
    "TRADE": "122",
    "VALUE (mn)": "1.855",
    "VOLUME": "511062"
  },
  {
    "#": "47",
    "DATE": "2026-05-04",
    "TRADING CODE": "RINGSHINE",
    "LTP*": "3.7",
    "HIGH": "3.7",
    "LOW": "3.6",
    "OPENP*": "3.6",
    "CLOSEP*": "3.6",
    "YCP": "3.6",
    "TRADE": "90",
    "VALUE (mn)": "1.601",
    "VOLUME": "442651"
  },
  {
    "#": "46",
    "DATE": "2026-05-05",
    "TRADING CODE": "RINGSHINE",
    "LTP*": "3.6",
    "HIGH": "3.7",
    "LOW": "3.5",
    "OPENP*": "3.7",
    "CLOSEP*": "3.5",
    "YCP": "3.6",
    "TRADE": "200",
    "VALUE (mn)": "3.035",
    "VOLUME": "857859"
  },
  {
    "#": "45",
    "DATE": "2026-05-06",
    "TRADING CODE": "RINGSHINE",
    "LTP*": "3.6",
    "HIGH": "3.6",
    "LOW": "3.4",
    "OPENP*": "3.5",
    "CLOSEP*": "3.5",
    "YCP": "3.5",
    "TRADE": "110",
    "VALUE (mn)": "1.438",
    "VOLUME": "411202"
  },
  {
    "#": "44",
    "DATE": "2026-05-07",
    "TRADING CODE": "RINGSHINE",
    "LTP*": "3.5",
    "HIGH": "3.7",
    "LOW": "3.5",
    "OPENP*": "3.6",
    "CLOSEP*": "3.5",
    "YCP": "3.5",
    "TRADE": "170",
    "VALUE (mn)": "2.801",
    "VOLUME": "790403"
  },
  {
    "#": "43",
    "DATE": "2026-05-10",
    "TRADING CODE": "RINGSHINE",
    "LTP*": "3.5",
    "HIGH": "3.6",
    "LOW": "3.5",
    "OPENP*": "3.5",
    "CLOSEP*": "3.5",
    "YCP": "3.5",
    "TRADE": "73",
    "VALUE (mn)": "1.082",
    "VOLUME": "309024"
  },
  {
    "#": "42",
    "DATE": "2026-05-11",
    "TRADING CODE": "RINGSHINE",
    "LTP*": "3.4",
    "HIGH": "3.6",
    "LOW": "3.4",
    "OPENP*": "3.5",
    "CLOSEP*": "3.4",
    "YCP": "3.5",
    "TRADE": "133",
    "VALUE (mn)": "3.032",
    "VOLUME": "883004"
  },
  {
    "#": "41",
    "DATE": "2026-05-12",
    "TRADING CODE": "RINGSHINE",
    "LTP*": "3.5",
    "HIGH": "3.5",
    "LOW": "3.3",
    "OPENP*": "3.4",
    "CLOSEP*": "3.5",
    "YCP": "3.4",
    "TRADE": "142",
    "VALUE (mn)": "1.913",
    "VOLUME": "561048"
  },
  {
    "#": "40",
    "DATE": "2026-05-13",
    "TRADING CODE": "RINGSHINE",
    "LTP*": "3.5",
    "HIGH": "3.6",
    "LOW": "3.4",
    "OPENP*": "3.5",
    "CLOSEP*": "3.5",
    "YCP": "3.5",
    "TRADE": "106",
    "VALUE (mn)": "2.906",
    "VOLUME": "824149"
  },
  {
    "#": "39",
    "DATE": "2026-05-14",
    "TRADING CODE": "RINGSHINE",
    "LTP*": "3.6",
    "HIGH": "3.6",
    "LOW": "3.5",
    "OPENP*": "3.6",
    "CLOSEP*": "3.6",
    "YCP": "3.5",
    "TRADE": "91",
    "VALUE (mn)": "1.385",
    "VOLUME": "388349"
  },
  {
    "#": "38",
    "DATE": "2026-05-17",
    "TRADING CODE": "RINGSHINE",
    "LTP*": "3.7",
    "HIGH": "3.7",
    "LOW": "3.5",
    "OPENP*": "3.6",
    "CLOSEP*": "3.6",
    "YCP": "3.6",
    "TRADE": "145",
    "VALUE (mn)": "1.296",
    "VOLUME": "359697"
  },
  {
    "#": "37",
    "DATE": "2026-05-18",
    "TRADING CODE": "RINGSHINE",
    "LTP*": "3.6",
    "HIGH": "3.6",
    "LOW": "3.5",
    "OPENP*": "3.6",
    "CLOSEP*": "3.5",
    "YCP": "3.6",
    "TRADE": "99",
    "VALUE (mn)": "1.328",
    "VOLUME": "375820"
  },
  {
    "#": "36",
    "DATE": "2026-05-19",
    "TRADING CODE": "RINGSHINE",
    "LTP*": "3.5",
    "HIGH": "3.6",
    "LOW": "3.4",
    "OPENP*": "3.5",
    "CLOSEP*": "3.5",
    "YCP": "3.5",
    "TRADE": "118",
    "VALUE (mn)": "1.411",
    "VOLUME": "403880"
  },
  {
    "#": "35",
    "DATE": "2026-05-20",
    "TRADING CODE": "RINGSHINE",
    "LTP*": "3.5",
    "HIGH": "3.6",
    "LOW": "3.3",
    "OPENP*": "3.4",
    "CLOSEP*": "3.5",
    "YCP": "3.5",
    "TRADE": "173",
    "VALUE (mn)": "2.033",
    "VOLUME": "583446"
  },
  {
    "#": "34",
    "DATE": "2026-05-21",
    "TRADING CODE": "RINGSHINE",
    "LTP*": "3.5",
    "HIGH": "3.6",
    "LOW": "3.5",
    "OPENP*": "3.5",
    "CLOSEP*": "3.5",
    "YCP": "3.5",
    "TRADE": "92",
    "VALUE (mn)": "1.843",
    "VOLUME": "526024"
  },
  {
    "#": "33",
    "DATE": "2026-05-23",
    "TRADING CODE": "RINGSHINE",
    "LTP*": "3.6",
    "HIGH": "3.6",
    "LOW": "3.5",
    "OPENP*": "3.5",
    "CLOSEP*": "3.5",
    "YCP": "3.5",
    "TRADE": "99",
    "VALUE (mn)": "1.404",
    "VOLUME": "396262"
  },
  {
    "#": "32",
    "DATE": "2026-05-24",
    "TRADING CODE": "RINGSHINE",
    "LTP*": "3.7",
    "HIGH": "3.7",
    "LOW": "3.6",
    "OPENP*": "3.6",
    "CLOSEP*": "3.7",
    "YCP": "3.5",
    "TRADE": "233",
    "VALUE (mn)": "4.292",
    "VOLUME": "1188946"
  },
  {
    "#": "31",
    "DATE": "2026-06-01",
    "TRADING CODE": "RINGSHINE",
    "LTP*": "3.7",
    "HIGH": "3.8",
    "LOW": "3.6",
    "OPENP*": "3.7",
    "CLOSEP*": "3.6",
    "YCP": "3.7",
    "TRADE": "135",
    "VALUE (mn)": "1.438",
    "VOLUME": "394963"
  },
  {
    "#": "30",
    "DATE": "2026-06-02",
    "TRADING CODE": "RINGSHINE",
    "LTP*": "3.6",
    "HIGH": "3.7",
    "LOW": "3.5",
    "OPENP*": "3.6",
    "CLOSEP*": "3.6",
    "YCP": "3.6",
    "TRADE": "145",
    "VALUE (mn)": "1.644",
    "VOLUME": "456369"
  },
  {
    "#": "29",
    "DATE": "2026-06-03",
    "TRADING CODE": "RINGSHINE",
    "LTP*": "3.6",
    "HIGH": "3.7",
    "LOW": "3.6",
    "OPENP*": "3.6",
    "CLOSEP*": "3.6",
    "YCP": "3.6",
    "TRADE": "164",
    "VALUE (mn)": "3.25",
    "VOLUME": "895390"
  },
  {
    "#": "28",
    "DATE": "2026-06-04",
    "TRADING CODE": "RINGSHINE",
    "LTP*": "3.7",
    "HIGH": "3.7",
    "LOW": "3.6",
    "OPENP*": "3.6",
    "CLOSEP*": "3.6",
    "YCP": "3.6",
    "TRADE": "175",
    "VALUE (mn)": "4.08",
    "VOLUME": "1128966"
  },
  {
    "#": "27",
    "DATE": "2026-06-07",
    "TRADING CODE": "RINGSHINE",
    "LTP*": "3.6",
    "HIGH": "3.8",
    "LOW": "3.6",
    "OPENP*": "3.7",
    "CLOSEP*": "3.6",
    "YCP": "3.6",
    "TRADE": "259",
    "VALUE (mn)": "4.067",
    "VOLUME": "1104780"
  },
  {
    "#": "26",
    "DATE": "2026-06-08",
    "TRADING CODE": "RINGSHINE",
    "LTP*": "3.6",
    "HIGH": "3.7",
    "LOW": "3.6",
    "OPENP*": "3.6",
    "CLOSEP*": "3.6",
    "YCP": "3.6",
    "TRADE": "130",
    "VALUE (mn)": "1.662",
    "VOLUME": "461485"
  },
  {
    "#": "25",
    "DATE": "2026-06-09",
    "TRADING CODE": "RINGSHINE",
    "LTP*": "3.6",
    "HIGH": "3.7",
    "LOW": "3.5",
    "OPENP*": "3.7",
    "CLOSEP*": "3.5",
    "YCP": "3.6",
    "TRADE": "229",
    "VALUE (mn)": "3.867",
    "VOLUME": "1084234"
  },
  {
    "#": "24",
    "DATE": "2026-06-10",
    "TRADING CODE": "RINGSHINE",
    "LTP*": "3.6",
    "HIGH": "3.7",
    "LOW": "3.5",
    "OPENP*": "3.5",
    "CLOSEP*": "3.5",
    "YCP": "3.5",
    "TRADE": "187",
    "VALUE (mn)": "3.593",
    "VOLUME": "1000653"
  },
  {
    "#": "23",
    "DATE": "2026-06-11",
    "TRADING CODE": "RINGSHINE",
    "LTP*": "3.6",
    "HIGH": "3.7",
    "LOW": "3.5",
    "OPENP*": "3.6",
    "CLOSEP*": "3.6",
    "YCP": "3.5",
    "TRADE": "210",
    "VALUE (mn)": "3.884",
    "VOLUME": "1072519"
  },
  {
    "#": "22",
    "DATE": "2026-06-14",
    "TRADING CODE": "RINGSHINE",
    "LTP*": "3.6",
    "HIGH": "3.7",
    "LOW": "3.5",
    "OPENP*": "3.7",
    "CLOSEP*": "3.6",
    "YCP": "3.6",
    "TRADE": "230",
    "VALUE (mn)": "4.993",
    "VOLUME": "1411903"
  },
  {
    "#": "21",
    "DATE": "2026-06-15",
    "TRADING CODE": "RINGSHINE",
    "LTP*": "3.5",
    "HIGH": "3.7",
    "LOW": "3.5",
    "OPENP*": "3.6",
    "CLOSEP*": "3.5",
    "YCP": "3.6",
    "TRADE": "144",
    "VALUE (mn)": "2.283",
    "VOLUME": "642215"
  },
  {
    "#": "20",
    "DATE": "2026-06-16",
    "TRADING CODE": "RINGSHINE",
    "LTP*": "3.6",
    "HIGH": "3.7",
    "LOW": "3.6",
    "OPENP*": "3.6",
    "CLOSEP*": "3.6",
    "YCP": "3.5",
    "TRADE": "201",
    "VALUE (mn)": "5.475",
    "VOLUME": "1503758"
  },
  {
    "#": "19",
    "DATE": "2026-06-17",
    "TRADING CODE": "RINGSHINE",
    "LTP*": "3.9",
    "HIGH": "3.9",
    "LOW": "3.6",
    "OPENP*": "3.7",
    "CLOSEP*": "3.9",
    "YCP": "3.6",
    "TRADE": "433",
    "VALUE (mn)": "13.089",
    "VOLUME": "3399119"
  },
  {
    "#": "18",
    "DATE": "2026-06-18",
    "TRADING CODE": "RINGSHINE",
    "LTP*": "3.9",
    "HIGH": "4.2",
    "LOW": "3.8",
    "OPENP*": "4.1",
    "CLOSEP*": "3.9",
    "YCP": "3.9",
    "TRADE": "707",
    "VALUE (mn)": "18.984",
    "VOLUME": "4690405"
  },
  {
    "#": "17",
    "DATE": "2026-06-21",
    "TRADING CODE": "RINGSHINE",
    "LTP*": "3.7",
    "HIGH": "4",
    "LOW": "3.7",
    "OPENP*": "3.9",
    "CLOSEP*": "3.7",
    "YCP": "3.9",
    "TRADE": "311",
    "VALUE (mn)": "4.54",
    "VOLUME": "1187285"
  },
  {
    "#": "16",
    "DATE": "2026-06-22",
    "TRADING CODE": "RINGSHINE",
    "LTP*": "3.6",
    "HIGH": "3.9",
    "LOW": "3.6",
    "OPENP*": "3.9",
    "CLOSEP*": "3.6",
    "YCP": "3.7",
    "TRADE": "138",
    "VALUE (mn)": "1.561",
    "VOLUME": "426625"
  },
  {
    "#": "15",
    "DATE": "2026-06-23",
    "TRADING CODE": "RINGSHINE",
    "LTP*": "3.7",
    "HIGH": "3.7",
    "LOW": "3.5",
    "OPENP*": "3.7",
    "CLOSEP*": "3.6",
    "YCP": "3.6",
    "TRADE": "227",
    "VALUE (mn)": "3.288",
    "VOLUME": "914877"
  },
  {
    "#": "14",
    "DATE": "2026-06-24",
    "TRADING CODE": "RINGSHINE",
    "LTP*": "3.6",
    "HIGH": "3.7",
    "LOW": "3.6",
    "OPENP*": "3.7",
    "CLOSEP*": "3.6",
    "YCP": "3.6",
    "TRADE": "126",
    "VALUE (mn)": "1.166",
    "VOLUME": "323172"
  },
  {
    "#": "13",
    "DATE": "2026-06-25",
    "TRADING CODE": "RINGSHINE",
    "LTP*": "3.7",
    "HIGH": "3.7",
    "LOW": "3.6",
    "OPENP*": "3.6",
    "CLOSEP*": "3.6",
    "YCP": "3.6",
    "TRADE": "161",
    "VALUE (mn)": "2.321",
    "VOLUME": "638477"
  },
  {
    "#": "12",
    "DATE": "2026-06-28",
    "TRADING CODE": "RINGSHINE",
    "LTP*": "3.6",
    "HIGH": "3.7",
    "LOW": "3.6",
    "OPENP*": "3.7",
    "CLOSEP*": "3.6",
    "YCP": "3.6",
    "TRADE": "166",
    "VALUE (mn)": "2.446",
    "VOLUME": "675356"
  },
  {
    "#": "11",
    "DATE": "2026-06-29",
    "TRADING CODE": "RINGSHINE",
    "LTP*": "3.6",
    "HIGH": "3.7",
    "LOW": "3.6",
    "OPENP*": "3.6",
    "CLOSEP*": "3.6",
    "YCP": "3.6",
    "TRADE": "185",
    "VALUE (mn)": "2.716",
    "VOLUME": "751272"
  },
  {
    "#": "10",
    "DATE": "2026-06-30",
    "TRADING CODE": "RINGSHINE",
    "LTP*": "3.9",
    "HIGH": "3.9",
    "LOW": "3.6",
    "OPENP*": "3.6",
    "CLOSEP*": "3.8",
    "YCP": "3.6",
    "TRADE": "312",
    "VALUE (mn)": "5.672",
    "VOLUME": "1490916"
  },
  {
    "#": "9",
    "DATE": "2026-07-02",
    "TRADING CODE": "RINGSHINE",
    "LTP*": "3.7",
    "HIGH": "3.9",
    "LOW": "3.6",
    "OPENP*": "3.8",
    "CLOSEP*": "3.7",
    "YCP": "3.8",
    "TRADE": "231",
    "VALUE (mn)": "4.516",
    "VOLUME": "1209652"
  },
  {
    "#": "8",
    "DATE": "2026-07-05",
    "TRADING CODE": "RINGSHINE",
    "LTP*": "3.6",
    "HIGH": "3.8",
    "LOW": "3.6",
    "OPENP*": "3.7",
    "CLOSEP*": "3.6",
    "YCP": "3.7",
    "TRADE": "235",
    "VALUE (mn)": "2.305",
    "VOLUME": "624693"
  },
  {
    "#": "7",
    "DATE": "2026-07-06",
    "TRADING CODE": "RINGSHINE",
    "LTP*": "3.7",
    "HIGH": "3.8",
    "LOW": "3.6",
    "OPENP*": "3.7",
    "CLOSEP*": "3.7",
    "YCP": "3.6",
    "TRADE": "238",
    "VALUE (mn)": "3.997",
    "VOLUME": "1079892"
  },
  {
    "#": "6",
    "DATE": "2026-07-07",
    "TRADING CODE": "RINGSHINE",
    "LTP*": "3.7",
    "HIGH": "3.8",
    "LOW": "3.7",
    "OPENP*": "3.7",
    "CLOSEP*": "3.7",
    "YCP": "3.7",
    "TRADE": "191",
    "VALUE (mn)": "2.859",
    "VOLUME": "772586"
  },
  {
    "#": "5",
    "DATE": "2026-07-08",
    "TRADING CODE": "RINGSHINE",
    "LTP*": "3.7",
    "HIGH": "3.7",
    "LOW": "3.6",
    "OPENP*": "3.7",
    "CLOSEP*": "3.7",
    "YCP": "3.7",
    "TRADE": "113",
    "VALUE (mn)": "1.678",
    "VOLUME": "456726"
  },
  {
    "#": "4",
    "DATE": "2026-07-09",
    "TRADING CODE": "RINGSHINE",
    "LTP*": "3.8",
    "HIGH": "3.8",
    "LOW": "3.6",
    "OPENP*": "3.7",
    "CLOSEP*": "3.7",
    "YCP": "3.7",
    "TRADE": "186",
    "VALUE (mn)": "5.574",
    "VOLUME": "1506757"
  },
  {
    "#": "3",
    "DATE": "2026-07-12",
    "TRADING CODE": "RINGSHINE",
    "LTP*": "3.7",
    "HIGH": "3.8",
    "LOW": "3.6",
    "OPENP*": "3.7",
    "CLOSEP*": "3.7",
    "YCP": "3.7",
    "TRADE": "272",
    "VALUE (mn)": "4.747",
    "VOLUME": "1285833"
  },
  {
    "#": "2",
    "DATE": "2026-07-13",
    "TRADING CODE": "RINGSHINE",
    "LTP*": "3.7",
    "HIGH": "3.8",
    "LOW": "3.6",
    "OPENP*": "3.7",
    "CLOSEP*": "3.7",
    "YCP": "3.7",
    "TRADE": "175",
    "VALUE (mn)": "2.776",
    "VOLUME": "749805"
  },
  {
    "#": "1",
    "DATE": "2026-07-14",
    "TRADING CODE": "RINGSHINE",
    "LTP*": "4",
    "HIGH": "4",
    "LOW": "3.7",
    "OPENP*": "3.8",
    "CLOSEP*": "4",
    "YCP": "3.7",
    "TRADE": "663",
    "VALUE (mn)": "13.758",
    "VOLUME": "3546695"
  }
]