[
  {
    "#": "1",
    "TRADING CODE": "AAMRANET",
    "LTP*": "20.3",
    "HIGH": "20.9",
    "LOW": "20.2",
    "CLOSEP*": "20.3",
    "YCP*": "20.6",
    "% CHANGE": "-1.46",
    "TRADE": "251",
    "VALUE (mn)": "4.8940",
    "VOLUME": "240205"
  },
  {
    "#": "2",
    "TRADING CODE": "AAMRATECH",
    "LTP*": "17",
    "HIGH": "17.3",
    "LOW": "16.8",
    "CLOSEP*": "17",
    "YCP*": "16.9",
    "% CHANGE": "0.59",
    "TRADE": "127",
    "VALUE (mn)": "2.7120",
    "VOLUME": "160383"
  },
  {
    "#": "3",
    "TRADING CODE": "ABBANK",
    "LTP*": "5",
    "HIGH": "5",
    "LOW": "4.9",
    "CLOSEP*": "4.9",
    "YCP*": "5",
    "% CHANGE": "0",
    "TRADE": "106",
    "VALUE (mn)": "1.4770",
    "VOLUME": "298485"
  },
  {
    "#": "4",
    "TRADING CODE": "ACFL",
    "LTP*": "23.3",
    "HIGH": "23.8",
    "LOW": "23",
    "CLOSEP*": "23.4",
    "YCP*": "23.5",
    "% CHANGE": "-0.85",
    "TRADE": "129",
    "VALUE (mn)": "1.3720",
    "VOLUME": "59102"
  },
  {
    "#": "5",
    "TRADING CODE": "ACI",
    "LTP*": "203.9",
    "HIGH": "207",
    "LOW": "201.1",
    "CLOSEP*": "203.9",
    "YCP*": "204.8",
    "% CHANGE": "-0.44",
    "TRADE": "633",
    "VALUE (mn)": "24.1810",
    "VOLUME": "118473"
  },
  {
    "#": "6",
    "TRADING CODE": "ACIFORMULA",
    "LTP*": "180",
    "HIGH": "181.8",
    "LOW": "172",
    "CLOSEP*": "180",
    "YCP*": "175.6",
    "% CHANGE": "2.51",
    "TRADE": "3358",
    "VALUE (mn)": "178.4060",
    "VOLUME": "1001043"
  },
  {
    "#": "7",
    "TRADING CODE": "ACMELAB",
    "LTP*": "84",
    "HIGH": "86.4",
    "LOW": "83.1",
    "CLOSEP*": "84",
    "YCP*": "85.3",
    "% CHANGE": "-1.52",
    "TRADE": "1802",
    "VALUE (mn)": "63.5260",
    "VOLUME": "749927"
  },
  {
    "#": "8",
    "TRADING CODE": "ACMEPL",
    "LTP*": "22.7",
    "HIGH": "23.5",
    "LOW": "22.5",
    "CLOSEP*": "22.7",
    "YCP*": "23",
    "% CHANGE": "-1.30",
    "TRADE": "949",
    "VALUE (mn)": "27.8480",
    "VOLUME": "1216693"
  },
  {
    "#": "9",
    "TRADING CODE": "ACTIVEFINE",
    "LTP*": "6.8",
    "HIGH": "6.9",
    "LOW": "6.7",
    "CLOSEP*": "6.8",
    "YCP*": "6.8",
    "% CHANGE": "0",
    "TRADE": "131",
    "VALUE (mn)": "2.7020",
    "VOLUME": "398779"
  },
  {
    "#": "10",
    "TRADING CODE": "ADNTEL",
    "LTP*": "68.8",
    "HIGH": "70.5",
    "LOW": "68.7",
    "CLOSEP*": "68.8",
    "YCP*": "69",
    "% CHANGE": "-0.29",
    "TRADE": "748",
    "VALUE (mn)": "23.0520",
    "VOLUME": "332711"
  },
  {
    "#": "11",
    "TRADING CODE": "ADVENT",
    "LTP*": "15.7",
    "HIGH": "15.9",
    "LOW": "15.6",
    "CLOSEP*": "15.7",
    "YCP*": "15.6",
    "% CHANGE": "0.64",
    "TRADE": "160",
    "VALUE (mn)": "2.9660",
    "VOLUME": "188580"
  },
  {
    "#": "12",
    "TRADING CODE": "AFCAGRO",
    "LTP*": "7.2",
    "HIGH": "7.4",
    "LOW": "7.2",
    "CLOSEP*": "7.2",
    "YCP*": "7.3",
    "% CHANGE": "-1.37",
    "TRADE": "83",
    "VALUE (mn)": "1.0430",
    "VOLUME": "143965"
  },
  {
    "#": "13",
    "TRADING CODE": "AFTABAUTO",
    "LTP*": "31.6",
    "HIGH": "32",
    "LOW": "31.4",
    "CLOSEP*": "31.6",
    "YCP*": "31.7",
    "% CHANGE": "-0.32",
    "TRADE": "312",
    "VALUE (mn)": "6.0460",
    "VOLUME": "191107"
  },
  {
    "#": "14",
    "TRADING CODE": "AGNISYSL",
    "LTP*": "34.8",
    "HIGH": "35.9",
    "LOW": "33.7",
    "CLOSEP*": "34.8",
    "YCP*": "33.6",
    "% CHANGE": "3.57",
    "TRADE": "2776",
    "VALUE (mn)": "152.7630",
    "VOLUME": "4401950"
  },
  {
    "#": "15",
    "TRADING CODE": "AGRANINS",
    "LTP*": "29",
    "HIGH": "31.4",
    "LOW": "28.8",
    "CLOSEP*": "29",
    "YCP*": "31",
    "% CHANGE": "-6.45",
    "TRADE": "784",
    "VALUE (mn)": "16.5470",
    "VOLUME": "554562"
  },
  {
    "#": "16",
    "TRADING CODE": "AIL",
    "LTP*": "37.5",
    "HIGH": "38.4",
    "LOW": "37.4",
    "CLOSEP*": "37.5",
    "YCP*": "37.9",
    "% CHANGE": "-1.06",
    "TRADE": "434",
    "VALUE (mn)": "7.8000",
    "VOLUME": "207195"
  },
  {
    "#": "17",
    "TRADING CODE": "AL-HAJTEX",
    "LTP*": "112.6",
    "HIGH": "114.2",
    "LOW": "110.5",
    "CLOSEP*": "112.6",
    "YCP*": "110",
    "% CHANGE": "2.36",
    "TRADE": "3093",
    "VALUE (mn)": "81.6590",
    "VOLUME": "724802"
  },
  {
    "#": "18",
    "TRADING CODE": "ALARABANK",
    "LTP*": "17.4",
    "HIGH": "18",
    "LOW": "17.3",
    "CLOSEP*": "17.4",
    "YCP*": "17.3",
    "% CHANGE": "0.58",
    "TRADE": "134",
    "VALUE (mn)": "1.8800",
    "VOLUME": "107359"
  },
  {
    "#": "19",
    "TRADING CODE": "ALIF",
    "LTP*": "5.5",
    "HIGH": "5.6",
    "LOW": "5.5",
    "CLOSEP*": "5.5",
    "YCP*": "5.6",
    "% CHANGE": "-1.79",
    "TRADE": "164",
    "VALUE (mn)": "3.1850",
    "VOLUME": "578448"
  },
  {
    "#": "20",
    "TRADING CODE": "ALLTEX",
    "LTP*": "19.5",
    "HIGH": "19.7",
    "LOW": "19.2",
    "CLOSEP*": "19.5",
    "YCP*": "19.2",
    "% CHANGE": "1.56",
    "TRADE": "371",
    "VALUE (mn)": "13.7810",
    "VOLUME": "704606"
  },
  {
    "#": "21",
    "TRADING CODE": "AMANFEED",
    "LTP*": "37.8",
    "HIGH": "38.6",
    "LOW": "37.4",
    "CLOSEP*": "37.8",
    "YCP*": "37.8",
    "% CHANGE": "0",
    "TRADE": "1767",
    "VALUE (mn)": "95.3900",
    "VOLUME": "2517319"
  },
  {
    "#": "22",
    "TRADING CODE": "AMBEEPHA",
    "LTP*": "812.8",
    "HIGH": "833",
    "LOW": "801.6",
    "CLOSEP*": "812.8",
    "YCP*": "822.9",
    "% CHANGE": "-1.23",
    "TRADE": "252",
    "VALUE (mn)": "3.8120",
    "VOLUME": "4654"
  },
  {
    "#": "23",
    "TRADING CODE": "AMCL(PRAN)",
    "LTP*": "235",
    "HIGH": "238.8",
    "LOW": "234.5",
    "CLOSEP*": "235",
    "YCP*": "239.1",
    "% CHANGE": "-1.71",
    "TRADE": "137",
    "VALUE (mn)": "4.2530",
    "VOLUME": "18060"
  },
  {
    "#": "24",
    "TRADING CODE": "ANWARGALV",
    "LTP*": "115.3",
    "HIGH": "118",
    "LOW": "114.9",
    "CLOSEP*": "115.3",
    "YCP*": "117.6",
    "% CHANGE": "-1.96",
    "TRADE": "1487",
    "VALUE (mn)": "28.8100",
    "VOLUME": "247760"
  },
  {
    "#": "25",
    "TRADING CODE": "AOL",
    "LTP*": "17.4",
    "HIGH": "17.5",
    "LOW": "17.2",
    "CLOSEP*": "17.4",
    "YCP*": "17.4",
    "% CHANGE": "0",
    "TRADE": "119",
    "VALUE (mn)": "3.2240",
    "VOLUME": "184841"
  },
  {
    "#": "26",
    "TRADING CODE": "APEXFOODS",
    "LTP*": "287.5",
    "HIGH": "295.1",
    "LOW": "287",
    "CLOSEP*": "289",
    "YCP*": "295.4",
    "% CHANGE": "-2.67",
    "TRADE": "725",
    "VALUE (mn)": "10.7910",
    "VOLUME": "37093"
  },
  {
    "#": "27",
    "TRADING CODE": "APEXFOOT",
    "LTP*": "217.2",
    "HIGH": "222",
    "LOW": "216.2",
    "CLOSEP*": "217.2",
    "YCP*": "220.4",
    "% CHANGE": "-1.45",
    "TRADE": "1003",
    "VALUE (mn)": "33.4100",
    "VOLUME": "152866"
  },
  {
    "#": "28",
    "TRADING CODE": "APEXSPINN",
    "LTP*": "385.3",
    "HIGH": "395.3",
    "LOW": "379.5",
    "CLOSEP*": "385.3",
    "YCP*": "390.5",
    "% CHANGE": "-1.33",
    "TRADE": "881",
    "VALUE (mn)": "52.9000",
    "VOLUME": "137180"
  },
  {
    "#": "29",
    "TRADING CODE": "APEXTANRY",
    "LTP*": "108.3",
    "HIGH": "114.8",
    "LOW": "108",
    "CLOSEP*": "108.3",
    "YCP*": "111.8",
    "% CHANGE": "-3.13",
    "TRADE": "847",
    "VALUE (mn)": "20.5560",
    "VOLUME": "187803"
  },
  {
    "#": "30",
    "TRADING CODE": "ARAMIT",
    "LTP*": "202.9",
    "HIGH": "209.6",
    "LOW": "201.2",
    "CLOSEP*": "202.9",
    "YCP*": "207.5",
    "% CHANGE": "-2.22",
    "TRADE": "346",
    "VALUE (mn)": "3.2310",
    "VOLUME": "15921"
  },
  {
    "#": "31",
    "TRADING CODE": "ARGONDENIM",
    "LTP*": "20.8",
    "HIGH": "21.5",
    "LOW": "20.6",
    "CLOSEP*": "20.8",
    "YCP*": "20.9",
    "% CHANGE": "-0.48",
    "TRADE": "1056",
    "VALUE (mn)": "36.9280",
    "VOLUME": "1758690"
  },
  {
    "#": "32",
    "TRADING CODE": "ASIAINS",
    "LTP*": "42.7",
    "HIGH": "44.9",
    "LOW": "42.1",
    "CLOSEP*": "42.7",
    "YCP*": "44.5",
    "% CHANGE": "-4.04",
    "TRADE": "906",
    "VALUE (mn)": "25.3370",
    "VOLUME": "581265"
  },
  {
    "#": "33",
    "TRADING CODE": "ASIAPACINS",
    "LTP*": "45",
    "HIGH": "47.5",
    "LOW": "44.5",
    "CLOSEP*": "45",
    "YCP*": "47.1",
    "% CHANGE": "-4.46",
    "TRADE": "584",
    "VALUE (mn)": "22.2520",
    "VOLUME": "484973"
  },
  {
    "#": "34",
    "TRADING CODE": "ASIATICLAB",
    "LTP*": "131.2",
    "HIGH": "134.6",
    "LOW": "130",
    "CLOSEP*": "131.2",
    "YCP*": "133.5",
    "% CHANGE": "-1.72",
    "TRADE": "998",
    "VALUE (mn)": "50.8210",
    "VOLUME": "384904"
  },
  {
    "#": "35",
    "TRADING CODE": "AZIZPIPES",
    "LTP*": "76",
    "HIGH": "77.5",
    "LOW": "75.5",
    "CLOSEP*": "76",
    "YCP*": "77.1",
    "% CHANGE": "-1.43",
    "TRADE": "129",
    "VALUE (mn)": "1.1850",
    "VOLUME": "15522"
  },
  {
    "#": "36",
    "TRADING CODE": "BANGAS",
    "LTP*": "138.4",
    "HIGH": "143.9",
    "LOW": "138",
    "CLOSEP*": "138.4",
    "YCP*": "139.9",
    "% CHANGE": "-1.07",
    "TRADE": "495",
    "VALUE (mn)": "8.8070",
    "VOLUME": "63140"
  },
  {
    "#": "37",
    "TRADING CODE": "BANKASIA",
    "LTP*": "18.3",
    "HIGH": "18.6",
    "LOW": "18.2",
    "CLOSEP*": "18.3",
    "YCP*": "18.4",
    "% CHANGE": "-0.54",
    "TRADE": "253",
    "VALUE (mn)": "4.5320",
    "VOLUME": "246383"
  },
  {
    "#": "38",
    "TRADING CODE": "BARKAPOWER",
    "LTP*": "8",
    "HIGH": "8.2",
    "LOW": "7.9",
    "CLOSEP*": "8",
    "YCP*": "8",
    "% CHANGE": "0",
    "TRADE": "227",
    "VALUE (mn)": "4.1780",
    "VOLUME": "522354"
  },
  {
    "#": "39",
    "TRADING CODE": "BATASHOE",
    "LTP*": "887.5",
    "HIGH": "892.9",
    "LOW": "887.5",
    "CLOSEP*": "888",
    "YCP*": "888",
    "% CHANGE": "-0.06",
    "TRADE": "65",
    "VALUE (mn)": "0.5540",
    "VOLUME": "624"
  },
  {
    "#": "40",
    "TRADING CODE": "BATBC",
    "LTP*": "221.3",
    "HIGH": "222.6",
    "LOW": "220.7",
    "CLOSEP*": "221.3",
    "YCP*": "222.7",
    "% CHANGE": "-0.63",
    "TRADE": "1082",
    "VALUE (mn)": "20.0940",
    "VOLUME": "90674"
  },
  {
    "#": "41",
    "TRADING CODE": "BAYLEASING",
    "LTP*": "4.7",
    "HIGH": "4.7",
    "LOW": "4.5",
    "CLOSEP*": "4.7",
    "YCP*": "4.5",
    "% CHANGE": "4.44",
    "TRADE": "92",
    "VALUE (mn)": "1.6870",
    "VOLUME": "361786"
  },
  {
    "#": "42",
    "TRADING CODE": "BBS",
    "LTP*": "14.9",
    "HIGH": "15.3",
    "LOW": "14.8",
    "CLOSEP*": "14.9",
    "YCP*": "15.1",
    "% CHANGE": "-1.32",
    "TRADE": "570",
    "VALUE (mn)": "13.2930",
    "VOLUME": "884825"
  },
  {
    "#": "43",
    "TRADING CODE": "BBSCABLES",
    "LTP*": "22.5",
    "HIGH": "22.9",
    "LOW": "22.5",
    "CLOSEP*": "22.5",
    "YCP*": "22.7",
    "% CHANGE": "-0.88",
    "TRADE": "1144",
    "VALUE (mn)": "39.6610",
    "VOLUME": "1749901"
  },
  {
    "#": "44",
    "TRADING CODE": "BDAUTOCA",
    "LTP*": "209.9",
    "HIGH": "215",
    "LOW": "209.1",
    "CLOSEP*": "209.9",
    "YCP*": "212.1",
    "% CHANGE": "-1.04",
    "TRADE": "742",
    "VALUE (mn)": "11.7390",
    "VOLUME": "55495"
  },
  {
    "#": "45",
    "TRADING CODE": "BDCOM",
    "LTP*": "34.1",
    "HIGH": "36.8",
    "LOW": "33.6",
    "CLOSEP*": "34.1",
    "YCP*": "33.5",
    "% CHANGE": "1.79",
    "TRADE": "1474",
    "VALUE (mn)": "73.6340",
    "VOLUME": "2159214"
  },
  {
    "#": "46",
    "TRADING CODE": "BDFINANCE",
    "LTP*": "12.8",
    "HIGH": "13",
    "LOW": "12.7",
    "CLOSEP*": "12.8",
    "YCP*": "12.8",
    "% CHANGE": "0",
    "TRADE": "186",
    "VALUE (mn)": "5.4510",
    "VOLUME": "424260"
  },
  {
    "#": "47",
    "TRADING CODE": "BDLAMPS",
    "LTP*": "181.5",
    "HIGH": "184.9",
    "LOW": "180.4",
    "CLOSEP*": "181.5",
    "YCP*": "184.4",
    "% CHANGE": "-1.57",
    "TRADE": "357",
    "VALUE (mn)": "6.9490",
    "VOLUME": "38121"
  },
  {
    "#": "48",
    "TRADING CODE": "BDTHAI",
    "LTP*": "18.6",
    "HIGH": "19.1",
    "LOW": "18.6",
    "CLOSEP*": "18.6",
    "YCP*": "18.9",
    "% CHANGE": "-1.59",
    "TRADE": "1325",
    "VALUE (mn)": "41.6600",
    "VOLUME": "2220984"
  },
  {
    "#": "49",
    "TRADING CODE": "BDTHAIFOOD",
    "LTP*": "22",
    "HIGH": "23.5",
    "LOW": "21.7",
    "CLOSEP*": "22",
    "YCP*": "23",
    "% CHANGE": "-4.35",
    "TRADE": "1633",
    "VALUE (mn)": "38.7900",
    "VOLUME": "1734651"
  },
  {
    "#": "50",
    "TRADING CODE": "BDWELDING",
    "LTP*": "14.2",
    "HIGH": "14.3",
    "LOW": "13.8",
    "CLOSEP*": "14.2",
    "YCP*": "14",
    "% CHANGE": "1.43",
    "TRADE": "153",
    "VALUE (mn)": "1.6910",
    "VOLUME": "120738"
  },
  {
    "#": "51",
    "TRADING CODE": "BEACHHATCH",
    "LTP*": "34.3",
    "HIGH": "35.3",
    "LOW": "34.2",
    "CLOSEP*": "34.3",
    "YCP*": "35",
    "% CHANGE": "-2",
    "TRADE": "504",
    "VALUE (mn)": "12.8460",
    "VOLUME": "371619"
  },
  {
    "#": "52",
    "TRADING CODE": "BEACONPHAR",
    "LTP*": "110.1",
    "HIGH": "113",
    "LOW": "109.5",
    "CLOSEP*": "110.1",
    "YCP*": "112.2",
    "% CHANGE": "-1.87",
    "TRADE": "1553",
    "VALUE (mn)": "55.9920",
    "VOLUME": "503762"
  },
  {
    "#": "53",
    "TRADING CODE": "BENGALWTL",
    "LTP*": "24.5",
    "HIGH": "25.4",
    "LOW": "24.3",
    "CLOSEP*": "24.5",
    "YCP*": "25",
    "% CHANGE": "-2",
    "TRADE": "374",
    "VALUE (mn)": "8.5660",
    "VOLUME": "347004"
  },
  {
    "#": "54",
    "TRADING CODE": "BERGERPBL",
    "LTP*": "1406",
    "HIGH": "1409",
    "LOW": "1403.1",
    "CLOSEP*": "1405.6",
    "YCP*": "1406.5",
    "% CHANGE": "-0.04",
    "TRADE": "266",
    "VALUE (mn)": "6.4090",
    "VOLUME": "4561"
  },
  {
    "#": "55",
    "TRADING CODE": "BESTHLDNG",
    "LTP*": "16.4",
    "HIGH": "16.6",
    "LOW": "16.2",
    "CLOSEP*": "16.4",
    "YCP*": "16.4",
    "% CHANGE": "0",
    "TRADE": "414",
    "VALUE (mn)": "12.5340",
    "VOLUME": "766146"
  },
  {
    "#": "56",
    "TRADING CODE": "BGIC",
    "LTP*": "41.9",
    "HIGH": "43.5",
    "LOW": "41.4",
    "CLOSEP*": "41.9",
    "YCP*": "43",
    "% CHANGE": "-2.56",
    "TRADE": "313",
    "VALUE (mn)": "10.6950",
    "VOLUME": "253068"
  },
  {
    "#": "57",
    "TRADING CODE": "BNICL",
    "LTP*": "111.6",
    "HIGH": "113",
    "LOW": "110.7",
    "CLOSEP*": "111.6",
    "YCP*": "111.1",
    "% CHANGE": "0.45",
    "TRADE": "318",
    "VALUE (mn)": "18.2030",
    "VOLUME": "163025"
  },
  {
    "#": "58",
    "TRADING CODE": "BPML",
    "LTP*": "28.7",
    "HIGH": "29.9",
    "LOW": "28.6",
    "CLOSEP*": "28.7",
    "YCP*": "29.4",
    "% CHANGE": "-2.38",
    "TRADE": "202",
    "VALUE (mn)": "3.8210",
    "VOLUME": "132113"
  },
  {
    "#": "59",
    "TRADING CODE": "BPPL",
    "LTP*": "20.4",
    "HIGH": "20.8",
    "LOW": "20.3",
    "CLOSEP*": "20.4",
    "YCP*": "20.6",
    "% CHANGE": "-0.97",
    "TRADE": "885",
    "VALUE (mn)": "31.9520",
    "VOLUME": "1560769"
  },
  {
    "#": "60",
    "TRADING CODE": "BRACBANK",
    "LTP*": "63.9",
    "HIGH": "64.7",
    "LOW": "63.5",
    "CLOSEP*": "63.9",
    "YCP*": "64.6",
    "% CHANGE": "-1.08",
    "TRADE": "2841",
    "VALUE (mn)": "154.0320",
    "VOLUME": "2413752"
  },
  {
    "#": "61",
    "TRADING CODE": "BSC",
    "LTP*": "124.7",
    "HIGH": "126.2",
    "LOW": "123.3",
    "CLOSEP*": "124.7",
    "YCP*": "126.4",
    "% CHANGE": "-1.34",
    "TRADE": "3462",
    "VALUE (mn)": "189.5970",
    "VOLUME": "1522153"
  },
  {
    "#": "62",
    "TRADING CODE": "BSCPLC",
    "LTP*": "163",
    "HIGH": "165",
    "LOW": "160.1",
    "CLOSEP*": "163",
    "YCP*": "163.6",
    "% CHANGE": "-0.37",
    "TRADE": "999",
    "VALUE (mn)": "47.1950",
    "VOLUME": "290008"
  },
  {
    "#": "63",
    "TRADING CODE": "BSRMLTD",
    "LTP*": "106.5",
    "HIGH": "110.8",
    "LOW": "105.1",
    "CLOSEP*": "106.5",
    "YCP*": "109.4",
    "% CHANGE": "-2.65",
    "TRADE": "1801",
    "VALUE (mn)": "85.5550",
    "VOLUME": "790928"
  },
  {
    "#": "64",
    "TRADING CODE": "BSRMSTEEL",
    "LTP*": "100.7",
    "HIGH": "102",
    "LOW": "98",
    "CLOSEP*": "100.7",
    "YCP*": "99",
    "% CHANGE": "1.72",
    "TRADE": "3235",
    "VALUE (mn)": "221.4660",
    "VOLUME": "2196861"
  },
  {
    "#": "65",
    "TRADING CODE": "BXPHARMA",
    "LTP*": "152.4",
    "HIGH": "154.4",
    "LOW": "151.8",
    "CLOSEP*": "152.4",
    "YCP*": "153.3",
    "% CHANGE": "-0.59",
    "TRADE": "1873",
    "VALUE (mn)": "113.6220",
    "VOLUME": "741596"
  },
  {
    "#": "66",
    "TRADING CODE": "CENTRALINS",
    "LTP*": "43",
    "HIGH": "44.7",
    "LOW": "42.6",
    "CLOSEP*": "43",
    "YCP*": "44.4",
    "% CHANGE": "-3.15",
    "TRADE": "611",
    "VALUE (mn)": "23.9640",
    "VOLUME": "545408"
  },
  {
    "#": "67",
    "TRADING CODE": "CENTRALPHL",
    "LTP*": "10.8",
    "HIGH": "11",
    "LOW": "10.6",
    "CLOSEP*": "10.8",
    "YCP*": "10.5",
    "% CHANGE": "2.86",
    "TRADE": "537",
    "VALUE (mn)": "13.7700",
    "VOLUME": "1272071"
  },
  {
    "#": "68",
    "TRADING CODE": "CITYBANK",
    "LTP*": "31.4",
    "HIGH": "31.8",
    "LOW": "31.3",
    "CLOSEP*": "31.4",
    "YCP*": "31.6",
    "% CHANGE": "-0.63",
    "TRADE": "1366",
    "VALUE (mn)": "118.7350",
    "VOLUME": "3777578"
  },
  {
    "#": "69",
    "TRADING CODE": "CITYGENINS",
    "LTP*": "107.3",
    "HIGH": "107.4",
    "LOW": "106.5",
    "CLOSEP*": "107.2",
    "YCP*": "107.2",
    "% CHANGE": "0.09",
    "TRADE": "361",
    "VALUE (mn)": "29.7630",
    "VOLUME": "277954"
  },
  {
    "#": "70",
    "TRADING CODE": "CLICL",
    "LTP*": "52.6",
    "HIGH": "55",
    "LOW": "52.2",
    "CLOSEP*": "52.6",
    "YCP*": "54.7",
    "% CHANGE": "-3.84",
    "TRADE": "918",
    "VALUE (mn)": "18.9900",
    "VOLUME": "357893"
  },
  {
    "#": "71",
    "TRADING CODE": "CNATEX",
    "LTP*": "3",
    "HIGH": "3",
    "LOW": "2.9",
    "CLOSEP*": "2.9",
    "YCP*": "2.9",
    "% CHANGE": "3.45",
    "TRADE": "108",
    "VALUE (mn)": "1.5990",
    "VOLUME": "549457"
  },
  {
    "#": "72",
    "TRADING CODE": "CONFIDCEM",
    "LTP*": "69.9",
    "HIGH": "72.5",
    "LOW": "69",
    "CLOSEP*": "69.9",
    "YCP*": "71.5",
    "% CHANGE": "-2.24",
    "TRADE": "1146",
    "VALUE (mn)": "35.7700",
    "VOLUME": "507619"
  },
  {
    "#": "73",
    "TRADING CODE": "CONTININS",
    "LTP*": "34.2",
    "HIGH": "36.2",
    "LOW": "34",
    "CLOSEP*": "34.2",
    "YCP*": "35.6",
    "% CHANGE": "-3.93",
    "TRADE": "746",
    "VALUE (mn)": "23.7750",
    "VOLUME": "681553"
  },
  {
    "#": "74",
    "TRADING CODE": "COPPERTECH",
    "LTP*": "26.2",
    "HIGH": "27.1",
    "LOW": "26",
    "CLOSEP*": "26.2",
    "YCP*": "26.9",
    "% CHANGE": "-2.60",
    "TRADE": "603",
    "VALUE (mn)": "13.8980",
    "VOLUME": "525171"
  },
  {
    "#": "75",
    "TRADING CODE": "CROWNCEMNT",
    "LTP*": "70.5",
    "HIGH": "71",
    "LOW": "69.1",
    "CLOSEP*": "70.5",
    "YCP*": "69.7",
    "% CHANGE": "1.15",
    "TRADE": "250",
    "VALUE (mn)": "6.4650",
    "VOLUME": "92221"
  },
  {
    "#": "76",
    "TRADING CODE": "CRYSTALINS",
    "LTP*": "70.4",
    "HIGH": "72.7",
    "LOW": "70",
    "CLOSEP*": "70.4",
    "YCP*": "72.1",
    "% CHANGE": "-2.36",
    "TRADE": "655",
    "VALUE (mn)": "15.9830",
    "VOLUME": "224683"
  },
  {
    "#": "77",
    "TRADING CODE": "CVOPRL",
    "LTP*": "176.3",
    "HIGH": "179.9",
    "LOW": "176",
    "CLOSEP*": "176.3",
    "YCP*": "178.6",
    "% CHANGE": "-1.29",
    "TRADE": "1648",
    "VALUE (mn)": "56.4610",
    "VOLUME": "318049"
  },
  {
    "#": "78",
    "TRADING CODE": "DACCADYE",
    "LTP*": "17.4",
    "HIGH": "17.5",
    "LOW": "17.2",
    "CLOSEP*": "17.4",
    "YCP*": "17.4",
    "% CHANGE": "0",
    "TRADE": "90",
    "VALUE (mn)": "1.0280",
    "VOLUME": "59214"
  },
  {
    "#": "79",
    "TRADING CODE": "DAFODILCOM",
    "LTP*": "163.8",
    "HIGH": "167.8",
    "LOW": "160.1",
    "CLOSEP*": "163.8",
    "YCP*": "165.6",
    "% CHANGE": "-1.09",
    "TRADE": "1031",
    "VALUE (mn)": "36.5030",
    "VOLUME": "220404"
  },
  {
    "#": "80",
    "TRADING CODE": "DBH",
    "LTP*": "41.7",
    "HIGH": "42.3",
    "LOW": "41.1",
    "CLOSEP*": "41.7",
    "YCP*": "41.6",
    "% CHANGE": "0.24",
    "TRADE": "254",
    "VALUE (mn)": "7.5690",
    "VOLUME": "181399"
  },
  {
    "#": "81",
    "TRADING CODE": "DELTALIFE",
    "LTP*": "81.8",
    "HIGH": "83.8",
    "LOW": "81.5",
    "CLOSEP*": "81.8",
    "YCP*": "84",
    "% CHANGE": "-2.62",
    "TRADE": "810",
    "VALUE (mn)": "24.8150",
    "VOLUME": "300600"
  },
  {
    "#": "82",
    "TRADING CODE": "DELTASPINN",
    "LTP*": "7.4",
    "HIGH": "7.6",
    "LOW": "7.3",
    "CLOSEP*": "7.4",
    "YCP*": "7.2",
    "% CHANGE": "2.78",
    "TRADE": "597",
    "VALUE (mn)": "15.2200",
    "VOLUME": "2031657"
  },
  {
    "#": "83",
    "TRADING CODE": "DESCO",
    "LTP*": "26.3",
    "HIGH": "26.6",
    "LOW": "26.1",
    "CLOSEP*": "26.2",
    "YCP*": "26.5",
    "% CHANGE": "-0.75",
    "TRADE": "86",
    "VALUE (mn)": "1.2620",
    "VOLUME": "48103"
  },
  {
    "#": "84",
    "TRADING CODE": "DESHBANDHU",
    "LTP*": "21.1",
    "HIGH": "21.6",
    "LOW": "21",
    "CLOSEP*": "21.1",
    "YCP*": "21.4",
    "% CHANGE": "-1.40",
    "TRADE": "471",
    "VALUE (mn)": "12.5640",
    "VOLUME": "590152"
  },
  {
    "#": "85",
    "TRADING CODE": "DGIC",
    "LTP*": "33.2",
    "HIGH": "35.4",
    "LOW": "32.6",
    "CLOSEP*": "33.2",
    "YCP*": "35",
    "% CHANGE": "-5.14",
    "TRADE": "624",
    "VALUE (mn)": "14.5790",
    "VOLUME": "428840"
  },
  {
    "#": "86",
    "TRADING CODE": "DHAKABANK",
    "LTP*": "12.2",
    "HIGH": "12.4",
    "LOW": "12.2",
    "CLOSEP*": "12.2",
    "YCP*": "12.3",
    "% CHANGE": "-0.81",
    "TRADE": "382",
    "VALUE (mn)": "10.4920",
    "VOLUME": "858188"
  },
  {
    "#": "87",
    "TRADING CODE": "DHAKAINS",
    "LTP*": "44.1",
    "HIGH": "45.9",
    "LOW": "43.5",
    "CLOSEP*": "44.1",
    "YCP*": "45.4",
    "% CHANGE": "-2.86",
    "TRADE": "234",
    "VALUE (mn)": "4.8480",
    "VOLUME": "108015"
  },
  {
    "#": "88",
    "TRADING CODE": "DOMINAGE",
    "LTP*": "75.8",
    "HIGH": "76",
    "LOW": "73.5",
    "CLOSEP*": "75.8",
    "YCP*": "74.9",
    "% CHANGE": "1.20",
    "TRADE": "1123",
    "VALUE (mn)": "53.9030",
    "VOLUME": "717500"
  },
  {
    "#": "89",
    "TRADING CODE": "DOREENPWR",
    "LTP*": "31.2",
    "HIGH": "31.6",
    "LOW": "31.1",
    "CLOSEP*": "31.2",
    "YCP*": "31.4",
    "% CHANGE": "-0.64",
    "TRADE": "549",
    "VALUE (mn)": "12.7960",
    "VOLUME": "408663"
  },
  {
    "#": "90",
    "TRADING CODE": "DSHGARME",
    "LTP*": "167.8",
    "HIGH": "170",
    "LOW": "160.1",
    "CLOSEP*": "167.8",
    "YCP*": "161.5",
    "% CHANGE": "3.90",
    "TRADE": "1444",
    "VALUE (mn)": "39.5580",
    "VOLUME": "239713"
  },
  {
    "#": "91",
    "TRADING CODE": "DSSL",
    "LTP*": "12.9",
    "HIGH": "13.2",
    "LOW": "12.4",
    "CLOSEP*": "12.9",
    "YCP*": "12.9",
    "% CHANGE": "0",
    "TRADE": "1122",
    "VALUE (mn)": "39.3860",
    "VOLUME": "3032642"
  },
  {
    "#": "92",
    "TRADING CODE": "DULAMIACOT",
    "LTP*": "202",
    "HIGH": "209",
    "LOW": "190.1",
    "CLOSEP*": "198.4",
    "YCP*": "191.6",
    "% CHANGE": "5.43",
    "TRADE": "206",
    "VALUE (mn)": "5.7490",
    "VOLUME": "29727"
  },
  {
    "#": "93",
    "TRADING CODE": "DUTCHBANGL",
    "LTP*": "50",
    "HIGH": "50.8",
    "LOW": "49.8",
    "CLOSEP*": "50",
    "YCP*": "51",
    "% CHANGE": "-1.96",
    "TRADE": "1153",
    "VALUE (mn)": "65.4270",
    "VOLUME": "1301893"
  },
  {
    "#": "94",
    "TRADING CODE": "EASTERNINS",
    "LTP*": "59",
    "HIGH": "62.3",
    "LOW": "58.6",
    "CLOSEP*": "59",
    "YCP*": "61.6",
    "% CHANGE": "-4.22",
    "TRADE": "326",
    "VALUE (mn)": "9.2430",
    "VOLUME": "154612"
  },
  {
    "#": "95",
    "TRADING CODE": "EASTLAND",
    "LTP*": "28",
    "HIGH": "30.2",
    "LOW": "27.7",
    "CLOSEP*": "28",
    "YCP*": "29.8",
    "% CHANGE": "-6.04",
    "TRADE": "771",
    "VALUE (mn)": "18.6620",
    "VOLUME": "646371"
  },
  {
    "#": "96",
    "TRADING CODE": "EASTRNLUB",
    "LTP*": "2000.6",
    "HIGH": "2017",
    "LOW": "1990.9",
    "CLOSEP*": "2000.6",
    "YCP*": "1984.1",
    "% CHANGE": "0.83",
    "TRADE": "2121",
    "VALUE (mn)": "49.4930",
    "VOLUME": "24702"
  },
  {
    "#": "97",
    "TRADING CODE": "EBL",
    "LTP*": "24.4",
    "HIGH": "24.5",
    "LOW": "24.3",
    "CLOSEP*": "24.4",
    "YCP*": "24.4",
    "% CHANGE": "0",
    "TRADE": "757",
    "VALUE (mn)": "29.7800",
    "VOLUME": "1221259"
  },
  {
    "#": "98",
    "TRADING CODE": "ECABLES",
    "LTP*": "144.8",
    "HIGH": "149.9",
    "LOW": "143.6",
    "CLOSEP*": "144.8",
    "YCP*": "145.7",
    "% CHANGE": "-0.62",
    "TRADE": "247",
    "VALUE (mn)": "3.2300",
    "VOLUME": "22137"
  },
  {
    "#": "99",
    "TRADING CODE": "EGEN",
    "LTP*": "27.4",
    "HIGH": "28.2",
    "LOW": "27.2",
    "CLOSEP*": "27.4",
    "YCP*": "27.5",
    "% CHANGE": "-0.36",
    "TRADE": "1100",
    "VALUE (mn)": "41.7370",
    "VOLUME": "1507216"
  },
  {
    "#": "100",
    "TRADING CODE": "EHL",
    "LTP*": "96.2",
    "HIGH": "98.2",
    "LOW": "95.6",
    "CLOSEP*": "96.2",
    "YCP*": "97.8",
    "% CHANGE": "-1.64",
    "TRADE": "1680",
    "VALUE (mn)": "56.5970",
    "VOLUME": "583221"
  },
  {
    "#": "101",
    "TRADING CODE": "EIL",
    "LTP*": "32.1",
    "HIGH": "33.8",
    "LOW": "31.8",
    "CLOSEP*": "32.1",
    "YCP*": "33.5",
    "% CHANGE": "-4.18",
    "TRADE": "923",
    "VALUE (mn)": "26.7020",
    "VOLUME": "815422"
  },
  {
    "#": "102",
    "TRADING CODE": "EMERALDOIL",
    "LTP*": "27.3",
    "HIGH": "28.5",
    "LOW": "27",
    "CLOSEP*": "27.3",
    "YCP*": "27.8",
    "% CHANGE": "-1.80",
    "TRADE": "702",
    "VALUE (mn)": "12.3670",
    "VOLUME": "447318"
  },
  {
    "#": "103",
    "TRADING CODE": "ENVOYTEX",
    "LTP*": "57",
    "HIGH": "58.4",
    "LOW": "56.5",
    "CLOSEP*": "57",
    "YCP*": "58.4",
    "% CHANGE": "-2.40",
    "TRADE": "700",
    "VALUE (mn)": "21.3850",
    "VOLUME": "372059"
  },
  {
    "#": "104",
    "TRADING CODE": "EPGL",
    "LTP*": "19.9",
    "HIGH": "20.3",
    "LOW": "19.8",
    "CLOSEP*": "19.9",
    "YCP*": "20",
    "% CHANGE": "-0.50",
    "TRADE": "477",
    "VALUE (mn)": "9.9680",
    "VOLUME": "498419"
  },
  {
    "#": "105",
    "TRADING CODE": "ESQUIRENIT",
    "LTP*": "26.2",
    "HIGH": "26.4",
    "LOW": "26",
    "CLOSEP*": "26.2",
    "YCP*": "26.2",
    "% CHANGE": "0",
    "TRADE": "169",
    "VALUE (mn)": "4.1110",
    "VOLUME": "156641"
  },
  {
    "#": "106",
    "TRADING CODE": "ETL",
    "LTP*": "14",
    "HIGH": "14.2",
    "LOW": "13.9",
    "CLOSEP*": "14",
    "YCP*": "14",
    "% CHANGE": "0",
    "TRADE": "1006",
    "VALUE (mn)": "34.8990",
    "VOLUME": "2489775"
  },
  {
    "#": "107",
    "TRADING CODE": "FAMILYTEX",
    "LTP*": "2.3",
    "HIGH": "2.4",
    "LOW": "2.3",
    "CLOSEP*": "2.3",
    "YCP*": "2.3",
    "% CHANGE": "0",
    "TRADE": "133",
    "VALUE (mn)": "1.4750",
    "VOLUME": "638109"
  },
  {
    "#": "108",
    "TRADING CODE": "FARCHEM",
    "LTP*": "24",
    "HIGH": "24.3",
    "LOW": "22.7",
    "CLOSEP*": "24",
    "YCP*": "23",
    "% CHANGE": "4.35",
    "TRADE": "1609",
    "VALUE (mn)": "52.1790",
    "VOLUME": "2199673"
  },
  {
    "#": "109",
    "TRADING CODE": "FAREASTLIF",
    "LTP*": "23",
    "HIGH": "23.2",
    "LOW": "22.9",
    "CLOSEP*": "23",
    "YCP*": "22.7",
    "% CHANGE": "1.32",
    "TRADE": "54",
    "VALUE (mn)": "0.4570",
    "VOLUME": "19892"
  },
  {
    "#": "110",
    "TRADING CODE": "FEDERALINS",
    "LTP*": "27.8",
    "HIGH": "29.2",
    "LOW": "27.6",
    "CLOSEP*": "27.8",
    "YCP*": "29.2",
    "% CHANGE": "-4.79",
    "TRADE": "1133",
    "VALUE (mn)": "35.6500",
    "VOLUME": "1258119"
  },
  {
    "#": "111",
    "TRADING CODE": "FEKDIL",
    "LTP*": "25.5",
    "HIGH": "26.1",
    "LOW": "25.2",
    "CLOSEP*": "25.5",
    "YCP*": "25",
    "% CHANGE": "2",
    "TRADE": "2260",
    "VALUE (mn)": "165.2310",
    "VOLUME": "6444729"
  },
  {
    "#": "112",
    "TRADING CODE": "FINEFOODS",
    "LTP*": "497.6",
    "HIGH": "499",
    "LOW": "490.5",
    "CLOSEP*": "497.6",
    "YCP*": "498.3",
    "% CHANGE": "-0.14",
    "TRADE": "416",
    "VALUE (mn)": "37.0000",
    "VOLUME": "74373"
  },
  {
    "#": "113",
    "TRADING CODE": "FORTUNE",
    "LTP*": "20.5",
    "HIGH": "21.3",
    "LOW": "20.4",
    "CLOSEP*": "20.5",
    "YCP*": "20.9",
    "% CHANGE": "-1.91",
    "TRADE": "1018",
    "VALUE (mn)": "24.5770",
    "VOLUME": "1182850"
  },
  {
    "#": "114",
    "TRADING CODE": "FUWANGCER",
    "LTP*": "15.8",
    "HIGH": "16.2",
    "LOW": "15.7",
    "CLOSEP*": "15.8",
    "YCP*": "16.1",
    "% CHANGE": "-1.86",
    "TRADE": "894",
    "VALUE (mn)": "37.3070",
    "VOLUME": "2341582"
  },
  {
    "#": "115",
    "TRADING CODE": "FUWANGFOOD",
    "LTP*": "12.7",
    "HIGH": "12.9",
    "LOW": "12.7",
    "CLOSEP*": "12.7",
    "YCP*": "12.8",
    "% CHANGE": "-0.78",
    "TRADE": "286",
    "VALUE (mn)": "8.9540",
    "VOLUME": "702489"
  },
  {
    "#": "116",
    "TRADING CODE": "GBBPOWER",
    "LTP*": "8.1",
    "HIGH": "8.4",
    "LOW": "8",
    "CLOSEP*": "8.1",
    "YCP*": "8.2",
    "% CHANGE": "-1.22",
    "TRADE": "123",
    "VALUE (mn)": "2.2850",
    "VOLUME": "281847"
  },
  {
    "#": "117",
    "TRADING CODE": "GEMINISEA",
    "LTP*": "129.7",
    "HIGH": "132.7",
    "LOW": "126.1",
    "CLOSEP*": "129.7",
    "YCP*": "128.1",
    "% CHANGE": "1.25",
    "TRADE": "377",
    "VALUE (mn)": "7.0280",
    "VOLUME": "54010"
  },
  {
    "#": "118",
    "TRADING CODE": "GENEXIL",
    "LTP*": "41",
    "HIGH": "41.9",
    "LOW": "39.8",
    "CLOSEP*": "41",
    "YCP*": "40.5",
    "% CHANGE": "1.23",
    "TRADE": "2101",
    "VALUE (mn)": "87.1420",
    "VOLUME": "2118066"
  },
  {
    "#": "119",
    "TRADING CODE": "GENNEXT",
    "LTP*": "2.8",
    "HIGH": "2.9",
    "LOW": "2.7",
    "CLOSEP*": "2.8",
    "YCP*": "2.7",
    "% CHANGE": "3.70",
    "TRADE": "126",
    "VALUE (mn)": "2.0050",
    "VOLUME": "718543"
  },
  {
    "#": "120",
    "TRADING CODE": "GHAIL",
    "LTP*": "15.2",
    "HIGH": "15.5",
    "LOW": "15.1",
    "CLOSEP*": "15.2",
    "YCP*": "15.4",
    "% CHANGE": "-1.30",
    "TRADE": "475",
    "VALUE (mn)": "15.0880",
    "VOLUME": "985613"
  },
  {
    "#": "121",
    "TRADING CODE": "GHCL",
    "LTP*": "23.6",
    "HIGH": "24.5",
    "LOW": "23.3",
    "CLOSEP*": "23.6",
    "YCP*": "22.9",
    "% CHANGE": "3.06",
    "TRADE": "528",
    "VALUE (mn)": "11.3200",
    "VOLUME": "477981"
  },
  {
    "#": "122",
    "TRADING CODE": "GLOBALINS",
    "LTP*": "41.9",
    "HIGH": "45.2",
    "LOW": "41.4",
    "CLOSEP*": "41.9",
    "YCP*": "45",
    "% CHANGE": "-6.89",
    "TRADE": "1634",
    "VALUE (mn)": "58.6670",
    "VOLUME": "1363016"
  },
  {
    "#": "123",
    "TRADING CODE": "GOLDENSON",
    "LTP*": "16.2",
    "HIGH": "16.6",
    "LOW": "16.2",
    "CLOSEP*": "16.2",
    "YCP*": "16.4",
    "% CHANGE": "-1.22",
    "TRADE": "785",
    "VALUE (mn)": "27.6330",
    "VOLUME": "1688000"
  },
  {
    "#": "124",
    "TRADING CODE": "GP",
    "LTP*": "256.3",
    "HIGH": "258",
    "LOW": "255.7",
    "CLOSEP*": "256.3",
    "YCP*": "257.5",
    "% CHANGE": "-0.47",
    "TRADE": "1718",
    "VALUE (mn)": "41.8270",
    "VOLUME": "162867"
  },
  {
    "#": "125",
    "TRADING CODE": "GPHISPAT",
    "LTP*": "19.5",
    "HIGH": "19.9",
    "LOW": "19.4",
    "CLOSEP*": "19.5",
    "YCP*": "19.7",
    "% CHANGE": "-1.02",
    "TRADE": "856",
    "VALUE (mn)": "38.7460",
    "VOLUME": "1976044"
  },
  {
    "#": "126",
    "TRADING CODE": "GQBALLPEN",
    "LTP*": "593.1",
    "HIGH": "605.3",
    "LOW": "588",
    "CLOSEP*": "593.1",
    "YCP*": "600.3",
    "% CHANGE": "-1.20",
    "TRADE": "777",
    "VALUE (mn)": "13.0950",
    "VOLUME": "21951"
  },
  {
    "#": "127",
    "TRADING CODE": "GREENDELT",
    "LTP*": "66.7",
    "HIGH": "68.4",
    "LOW": "66.5",
    "CLOSEP*": "66.7",
    "YCP*": "68.4",
    "% CHANGE": "-2.49",
    "TRADE": "460",
    "VALUE (mn)": "13.8970",
    "VOLUME": "206489"
  },
  {
    "#": "128",
    "TRADING CODE": "GSPFINANCE",
    "LTP*": "3.7",
    "HIGH": "3.7",
    "LOW": "3.5",
    "CLOSEP*": "3.7",
    "YCP*": "3.6",
    "% CHANGE": "2.78",
    "TRADE": "70",
    "VALUE (mn)": "0.4030",
    "VOLUME": "111232"
  },
  {
    "#": "129",
    "TRADING CODE": "HAKKANIPUL",
    "LTP*": "81.8",
    "HIGH": "84.4",
    "LOW": "81.5",
    "CLOSEP*": "81.8",
    "YCP*": "83.3",
    "% CHANGE": "-1.80",
    "TRADE": "1217",
    "VALUE (mn)": "27.0370",
    "VOLUME": "327656"
  },
  {
    "#": "130",
    "TRADING CODE": "HAMI",
    "LTP*": "162.6",
    "HIGH": "167.4",
    "LOW": "160.3",
    "CLOSEP*": "162.6",
    "YCP*": "163.3",
    "% CHANGE": "-0.43",
    "TRADE": "402",
    "VALUE (mn)": "5.8080",
    "VOLUME": "35553"
  },
  {
    "#": "131",
    "TRADING CODE": "HEIDELBCEM",
    "LTP*": "238.5",
    "HIGH": "246.4",
    "LOW": "238",
    "CLOSEP*": "238.8",
    "YCP*": "243.4",
    "% CHANGE": "-2.01",
    "TRADE": "459",
    "VALUE (mn)": "9.4980",
    "VOLUME": "39524"
  },
  {
    "#": "132",
    "TRADING CODE": "HRTEX",
    "LTP*": "21.6",
    "HIGH": "22",
    "LOW": "21.6",
    "CLOSEP*": "21.6",
    "YCP*": "21.7",
    "% CHANGE": "-0.46",
    "TRADE": "107",
    "VALUE (mn)": "1.8040",
    "VOLUME": "83011"
  },
  {
    "#": "133",
    "TRADING CODE": "HWAWELLTEX",
    "LTP*": "47.4",
    "HIGH": "47.8",
    "LOW": "47.1",
    "CLOSEP*": "47.4",
    "YCP*": "47.1",
    "% CHANGE": "0.64",
    "TRADE": "405",
    "VALUE (mn)": "8.6400",
    "VOLUME": "181901"
  },
  {
    "#": "134",
    "TRADING CODE": "IBNSINA",
    "LTP*": "326.9",
    "HIGH": "331.3",
    "LOW": "325.2",
    "CLOSEP*": "326.9",
    "YCP*": "332.6",
    "% CHANGE": "-1.71",
    "TRADE": "610",
    "VALUE (mn)": "15.6070",
    "VOLUME": "47592"
  },
  {
    "#": "135",
    "TRADING CODE": "IBP",
    "LTP*": "18.7",
    "HIGH": "19.2",
    "LOW": "18.6",
    "CLOSEP*": "18.7",
    "YCP*": "18.6",
    "% CHANGE": "0.54",
    "TRADE": "1651",
    "VALUE (mn)": "78.0820",
    "VOLUME": "4132352"
  },
  {
    "#": "136",
    "TRADING CODE": "ICB",
    "LTP*": "47.2",
    "HIGH": "47.9",
    "LOW": "47",
    "CLOSEP*": "47.2",
    "YCP*": "47.9",
    "% CHANGE": "-1.46",
    "TRADE": "418",
    "VALUE (mn)": "11.0200",
    "VOLUME": "232271"
  },
  {
    "#": "137",
    "TRADING CODE": "ICICL",
    "LTP*": "30.5",
    "HIGH": "32.2",
    "LOW": "30.2",
    "CLOSEP*": "30.5",
    "YCP*": "31.8",
    "% CHANGE": "-4.09",
    "TRADE": "624",
    "VALUE (mn)": "17.6730",
    "VOLUME": "567734"
  },
  {
    "#": "138",
    "TRADING CODE": "IDLC",
    "LTP*": "43.7",
    "HIGH": "44.6",
    "LOW": "43.5",
    "CLOSEP*": "43.7",
    "YCP*": "43.9",
    "% CHANGE": "-0.46",
    "TRADE": "756",
    "VALUE (mn)": "32.6210",
    "VOLUME": "740444"
  },
  {
    "#": "139",
    "TRADING CODE": "IFADAUTOS",
    "LTP*": "26.3",
    "HIGH": "26.7",
    "LOW": "26",
    "CLOSEP*": "26.3",
    "YCP*": "26.4",
    "% CHANGE": "-0.38",
    "TRADE": "440",
    "VALUE (mn)": "14.3970",
    "VOLUME": "545164"
  },
  {
    "#": "140",
    "TRADING CODE": "IFIC",
    "LTP*": "5",
    "HIGH": "5.1",
    "LOW": "4.9",
    "CLOSEP*": "5",
    "YCP*": "5",
    "% CHANGE": "0",
    "TRADE": "244",
    "VALUE (mn)": "8.4270",
    "VOLUME": "1689362"
  },
  {
    "#": "141",
    "TRADING CODE": "INDEXAGRO",
    "LTP*": "75.3",
    "HIGH": "76.7",
    "LOW": "75.2",
    "CLOSEP*": "75.3",
    "YCP*": "76.1",
    "% CHANGE": "-1.05",
    "TRADE": "444",
    "VALUE (mn)": "14.6760",
    "VOLUME": "193731"
  },
  {
    "#": "142",
    "TRADING CODE": "INTECH",
    "LTP*": "27.3",
    "HIGH": "27.7",
    "LOW": "27.2",
    "CLOSEP*": "27.3",
    "YCP*": "27.3",
    "% CHANGE": "0",
    "TRADE": "243",
    "VALUE (mn)": "3.5850",
    "VOLUME": "130782"
  },
  {
    "#": "143",
    "TRADING CODE": "INTRACO",
    "LTP*": "21.5",
    "HIGH": "22",
    "LOW": "21.5",
    "CLOSEP*": "21.5",
    "YCP*": "21.6",
    "% CHANGE": "-0.46",
    "TRADE": "214",
    "VALUE (mn)": "5.3290",
    "VOLUME": "246833"
  },
  {
    "#": "144",
    "TRADING CODE": "IPDC",
    "LTP*": "32.5",
    "HIGH": "33.4",
    "LOW": "32.1",
    "CLOSEP*": "32.5",
    "YCP*": "32.2",
    "% CHANGE": "0.93",
    "TRADE": "1621",
    "VALUE (mn)": "128.6170",
    "VOLUME": "3931073"
  },
  {
    "#": "145",
    "TRADING CODE": "ISLAMIBANK",
    "LTP*": "32.4",
    "HIGH": "32.8",
    "LOW": "32",
    "CLOSEP*": "32.4",
    "YCP*": "32.3",
    "% CHANGE": "0.31",
    "TRADE": "375",
    "VALUE (mn)": "6.5770",
    "VOLUME": "203783"
  },
  {
    "#": "146",
    "TRADING CODE": "ISLAMICFIN",
    "LTP*": "12.1",
    "HIGH": "12.3",
    "LOW": "11.8",
    "CLOSEP*": "12.1",
    "YCP*": "11.8",
    "% CHANGE": "2.54",
    "TRADE": "443",
    "VALUE (mn)": "13.0180",
    "VOLUME": "1077438"
  },
  {
    "#": "147",
    "TRADING CODE": "ISLAMIINS",
    "LTP*": "62.7",
    "HIGH": "63.9",
    "LOW": "62.4",
    "CLOSEP*": "62.7",
    "YCP*": "63.2",
    "% CHANGE": "-0.79",
    "TRADE": "454",
    "VALUE (mn)": "15.4120",
    "VOLUME": "243817"
  },
  {
    "#": "148",
    "TRADING CODE": "ISNLTD",
    "LTP*": "60.9",
    "HIGH": "62.4",
    "LOW": "60.6",
    "CLOSEP*": "60.9",
    "YCP*": "62.1",
    "% CHANGE": "-1.93",
    "TRADE": "708",
    "VALUE (mn)": "10.5190",
    "VOLUME": "171613"
  },
  {
    "#": "149",
    "TRADING CODE": "ITC",
    "LTP*": "51",
    "HIGH": "52.2",
    "LOW": "50.7",
    "CLOSEP*": "51",
    "YCP*": "51.4",
    "% CHANGE": "-0.78",
    "TRADE": "2284",
    "VALUE (mn)": "146.4230",
    "VOLUME": "2850504"
  },
  {
    "#": "150",
    "TRADING CODE": "JAMUNABANK",
    "LTP*": "23.7",
    "HIGH": "23.9",
    "LOW": "23.6",
    "CLOSEP*": "23.7",
    "YCP*": "23.8",
    "% CHANGE": "-0.42",
    "TRADE": "438",
    "VALUE (mn)": "20.6040",
    "VOLUME": "869712"
  },
  {
    "#": "151",
    "TRADING CODE": "JAMUNAOIL",
    "LTP*": "183.2",
    "HIGH": "185.9",
    "LOW": "182.5",
    "CLOSEP*": "183.4",
    "YCP*": "185.2",
    "% CHANGE": "-1.08",
    "TRADE": "273",
    "VALUE (mn)": "3.2330",
    "VOLUME": "17560"
  },
  {
    "#": "152",
    "TRADING CODE": "JANATAINS",
    "LTP*": "34.5",
    "HIGH": "36.1",
    "LOW": "34.4",
    "CLOSEP*": "34.5",
    "YCP*": "35.9",
    "% CHANGE": "-3.90",
    "TRADE": "614",
    "VALUE (mn)": "14.3590",
    "VOLUME": "410630"
  },
  {
    "#": "153",
    "TRADING CODE": "JHRML",
    "LTP*": "52",
    "HIGH": "53.1",
    "LOW": "51.6",
    "CLOSEP*": "52",
    "YCP*": "52.6",
    "% CHANGE": "-1.14",
    "TRADE": "552",
    "VALUE (mn)": "13.9900",
    "VOLUME": "266231"
  },
  {
    "#": "154",
    "TRADING CODE": "JMISMDL",
    "LTP*": "148.2",
    "HIGH": "152",
    "LOW": "145",
    "CLOSEP*": "148.2",
    "YCP*": "152",
    "% CHANGE": "-2.5",
    "TRADE": "192",
    "VALUE (mn)": "2.9600",
    "VOLUME": "19825"
  },
  {
    "#": "155",
    "TRADING CODE": "KARNAPHULI",
    "LTP*": "47",
    "HIGH": "50.1",
    "LOW": "46",
    "CLOSEP*": "47",
    "YCP*": "48.4",
    "% CHANGE": "-2.89",
    "TRADE": "1811",
    "VALUE (mn)": "91.6890",
    "VOLUME": "1882099"
  },
  {
    "#": "156",
    "TRADING CODE": "KAY&QUE",
    "LTP*": "429.6",
    "HIGH": "439.9",
    "LOW": "425",
    "CLOSEP*": "429.6",
    "YCP*": "438.2",
    "% CHANGE": "-1.96",
    "TRADE": "809",
    "VALUE (mn)": "20.8210",
    "VOLUME": "48111"
  },
  {
    "#": "157",
    "TRADING CODE": "KBPPWBIL",
    "LTP*": "40.4",
    "HIGH": "41.3",
    "LOW": "40.2",
    "CLOSEP*": "40.4",
    "YCP*": "40.7",
    "% CHANGE": "-0.74",
    "TRADE": "1434",
    "VALUE (mn)": "32.5300",
    "VOLUME": "799161"
  },
  {
    "#": "158",
    "TRADING CODE": "KDSALTD",
    "LTP*": "52.9",
    "HIGH": "54.1",
    "LOW": "52.8",
    "CLOSEP*": "52.9",
    "YCP*": "53",
    "% CHANGE": "-0.19",
    "TRADE": "982",
    "VALUE (mn)": "36.4000",
    "VOLUME": "683371"
  },
  {
    "#": "159",
    "TRADING CODE": "KEYACOSMET",
    "LTP*": "5.2",
    "HIGH": "5.3",
    "LOW": "5.1",
    "CLOSEP*": "5.2",
    "YCP*": "5.2",
    "% CHANGE": "0",
    "TRADE": "337",
    "VALUE (mn)": "7.7010",
    "VOLUME": "1478257"
  },
  {
    "#": "160",
    "TRADING CODE": "KOHINOOR",
    "LTP*": "529.4",
    "HIGH": "548.9",
    "LOW": "522.3",
    "CLOSEP*": "529.4",
    "YCP*": "540.3",
    "% CHANGE": "-2.02",
    "TRADE": "487",
    "VALUE (mn)": "9.0130",
    "VOLUME": "16852"
  },
  {
    "#": "161",
    "TRADING CODE": "KPCL",
    "LTP*": "10.2",
    "HIGH": "10.5",
    "LOW": "10.2",
    "CLOSEP*": "10.2",
    "YCP*": "10.3",
    "% CHANGE": "-0.97",
    "TRADE": "189",
    "VALUE (mn)": "3.5430",
    "VOLUME": "345934"
  },
  {
    "#": "162",
    "TRADING CODE": "KPPL",
    "LTP*": "14.9",
    "HIGH": "15.3",
    "LOW": "14.8",
    "CLOSEP*": "14.9",
    "YCP*": "15",
    "% CHANGE": "-0.67",
    "TRADE": "163",
    "VALUE (mn)": "2.2210",
    "VOLUME": "149089"
  },
  {
    "#": "163",
    "TRADING CODE": "KTL",
    "LTP*": "10.3",
    "HIGH": "10.6",
    "LOW": "10.2",
    "CLOSEP*": "10.3",
    "YCP*": "10.5",
    "% CHANGE": "-1.90",
    "TRADE": "215",
    "VALUE (mn)": "2.8650",
    "VOLUME": "276283"
  },
  {
    "#": "164",
    "TRADING CODE": "LANKABAFIN",
    "LTP*": "17.9",
    "HIGH": "18.5",
    "LOW": "17.1",
    "CLOSEP*": "17.9",
    "YCP*": "17.2",
    "% CHANGE": "4.07",
    "TRADE": "4664",
    "VALUE (mn)": "216.4810",
    "VOLUME": "12102722"
  },
  {
    "#": "165",
    "TRADING CODE": "LEGACYFOOT",
    "LTP*": "69.5",
    "HIGH": "71.1",
    "LOW": "69",
    "CLOSEP*": "69.5",
    "YCP*": "70.6",
    "% CHANGE": "-1.56",
    "TRADE": "492",
    "VALUE (mn)": "11.1350",
    "VOLUME": "158568"
  },
  {
    "#": "166",
    "TRADING CODE": "LHB",
    "LTP*": "60.2",
    "HIGH": "61",
    "LOW": "59.7",
    "CLOSEP*": "60.2",
    "YCP*": "60.7",
    "% CHANGE": "-0.82",
    "TRADE": "2001",
    "VALUE (mn)": "122.4410",
    "VOLUME": "2038750"
  },
  {
    "#": "167",
    "TRADING CODE": "LIBRAINFU",
    "LTP*": "654.4",
    "HIGH": "670",
    "LOW": "653",
    "CLOSEP*": "654.4",
    "YCP*": "661.4",
    "% CHANGE": "-1.06",
    "TRADE": "397",
    "VALUE (mn)": "5.3990",
    "VOLUME": "8172"
  },
  {
    "#": "168",
    "TRADING CODE": "LINDEBD",
    "LTP*": "744.4",
    "HIGH": "753",
    "LOW": "742.7",
    "CLOSEP*": "744.4",
    "YCP*": "749",
    "% CHANGE": "-0.61",
    "TRADE": "331",
    "VALUE (mn)": "4.6880",
    "VOLUME": "6290"
  },
  {
    "#": "169",
    "TRADING CODE": "LOVELLO",
    "LTP*": "72.2",
    "HIGH": "74.8",
    "LOW": "71.8",
    "CLOSEP*": "72.2",
    "YCP*": "73.8",
    "% CHANGE": "-2.17",
    "TRADE": "4012",
    "VALUE (mn)": "160.0810",
    "VOLUME": "2194839"
  },
  {
    "#": "170",
    "TRADING CODE": "LRBDL",
    "LTP*": "15.1",
    "HIGH": "15.4",
    "LOW": "14.9",
    "CLOSEP*": "15.1",
    "YCP*": "14.9",
    "% CHANGE": "1.34",
    "TRADE": "415",
    "VALUE (mn)": "12.4770",
    "VOLUME": "821458"
  },
  {
    "#": "171",
    "TRADING CODE": "MAGURAPLEX",
    "LTP*": "93",
    "HIGH": "94.6",
    "LOW": "92.7",
    "CLOSEP*": "93",
    "YCP*": "93.8",
    "% CHANGE": "-0.85",
    "TRADE": "884",
    "VALUE (mn)": "15.8950",
    "VOLUME": "170082"
  },
  {
    "#": "172",
    "TRADING CODE": "MAKSONSPIN",
    "LTP*": "6",
    "HIGH": "6",
    "LOW": "5.7",
    "CLOSEP*": "5.9",
    "YCP*": "5.7",
    "% CHANGE": "5.26",
    "TRADE": "120",
    "VALUE (mn)": "3.7360",
    "VOLUME": "631196"
  },
  {
    "#": "173",
    "TRADING CODE": "MALEKSPIN",
    "LTP*": "44.6",
    "HIGH": "45.3",
    "LOW": "42.3",
    "CLOSEP*": "44.6",
    "YCP*": "43.7",
    "% CHANGE": "2.06",
    "TRADE": "3014",
    "VALUE (mn)": "268.8040",
    "VOLUME": "6131291"
  },
  {
    "#": "174",
    "TRADING CODE": "MARICO",
    "LTP*": "2749.9",
    "HIGH": "2759.7",
    "LOW": "2746.4",
    "CLOSEP*": "2749.9",
    "YCP*": "2745.5",
    "% CHANGE": "0.16",
    "TRADE": "231",
    "VALUE (mn)": "5.2480",
    "VOLUME": "1908"
  },
  {
    "#": "175",
    "TRADING CODE": "MATINSPINN",
    "LTP*": "57.9",
    "HIGH": "58.5",
    "LOW": "57.7",
    "CLOSEP*": "57.9",
    "YCP*": "57.8",
    "% CHANGE": "0.17",
    "TRADE": "377",
    "VALUE (mn)": "15.0130",
    "VOLUME": "258535"
  },
  {
    "#": "176",
    "TRADING CODE": "MEGHNACEM",
    "LTP*": "32.6",
    "HIGH": "33.7",
    "LOW": "32.6",
    "CLOSEP*": "32.6",
    "YCP*": "32.9",
    "% CHANGE": "-0.91",
    "TRADE": "53",
    "VALUE (mn)": "0.6940",
    "VOLUME": "21113"
  },
  {
    "#": "177",
    "TRADING CODE": "MEGHNAINS",
    "LTP*": "39.1",
    "HIGH": "43.4",
    "LOW": "38.8",
    "CLOSEP*": "39.1",
    "YCP*": "42.9",
    "% CHANGE": "-8.86",
    "TRADE": "4229",
    "VALUE (mn)": "195.2160",
    "VOLUME": "4828740"
  },
  {
    "#": "178",
    "TRADING CODE": "MEGHNALIFE",
    "LTP*": "63.4",
    "HIGH": "65.4",
    "LOW": "63.2",
    "CLOSEP*": "63.4",
    "YCP*": "64.1",
    "% CHANGE": "-1.09",
    "TRADE": "383",
    "VALUE (mn)": "11.0400",
    "VOLUME": "173247"
  },
  {
    "#": "179",
    "TRADING CODE": "MERCANBANK",
    "LTP*": "7.6",
    "HIGH": "7.7",
    "LOW": "7.6",
    "CLOSEP*": "7.6",
    "YCP*": "7.6",
    "% CHANGE": "0",
    "TRADE": "80",
    "VALUE (mn)": "0.7840",
    "VOLUME": "103036"
  },
  {
    "#": "180",
    "TRADING CODE": "METROSPIN",
    "LTP*": "9.3",
    "HIGH": "9.4",
    "LOW": "9.2",
    "CLOSEP*": "9.3",
    "YCP*": "9.2",
    "% CHANGE": "1.09",
    "TRADE": "23",
    "VALUE (mn)": "0.1400",
    "VOLUME": "15029"
  },
  {
    "#": "181",
    "TRADING CODE": "MHSML",
    "LTP*": "23",
    "HIGH": "23.2",
    "LOW": "22.9",
    "CLOSEP*": "23",
    "YCP*": "23",
    "% CHANGE": "0",
    "TRADE": "890",
    "VALUE (mn)": "30.4570",
    "VOLUME": "1320629"
  },
  {
    "#": "182",
    "TRADING CODE": "MIDLANDBNK",
    "LTP*": "17.9",
    "HIGH": "18.7",
    "LOW": "17.8",
    "CLOSEP*": "17.9",
    "YCP*": "18.4",
    "% CHANGE": "-2.72",
    "TRADE": "1420",
    "VALUE (mn)": "62.2080",
    "VOLUME": "3436299"
  },
  {
    "#": "183",
    "TRADING CODE": "MIRACLEIND",
    "LTP*": "30.9",
    "HIGH": "31.8",
    "LOW": "30.3",
    "CLOSEP*": "30.9",
    "YCP*": "30.3",
    "% CHANGE": "1.98",
    "TRADE": "778",
    "VALUE (mn)": "18.9180",
    "VOLUME": "609888"
  },
  {
    "#": "184",
    "TRADING CODE": "MIRAKHTER",
    "LTP*": "42",
    "HIGH": "43.1",
    "LOW": "41.8",
    "CLOSEP*": "42",
    "YCP*": "42.3",
    "% CHANGE": "-0.71",
    "TRADE": "1644",
    "VALUE (mn)": "62.4060",
    "VOLUME": "1466547"
  },
  {
    "#": "185",
    "TRADING CODE": "MITHUNKNIT",
    "LTP*": "14.5",
    "HIGH": "15.8",
    "LOW": "14.5",
    "CLOSEP*": "14.5",
    "YCP*": "14.5",
    "% CHANGE": "0",
    "TRADE": "92",
    "VALUE (mn)": "1.7820",
    "VOLUME": "119518"
  },
  {
    "#": "186",
    "TRADING CODE": "MJLBD",
    "LTP*": "95.3",
    "HIGH": "96.7",
    "LOW": "95.1",
    "CLOSEP*": "95.3",
    "YCP*": "95.9",
    "% CHANGE": "-0.63",
    "TRADE": "419",
    "VALUE (mn)": "20.2580",
    "VOLUME": "211797"
  },
  {
    "#": "187",
    "TRADING CODE": "MLDYEING",
    "LTP*": "13.8",
    "HIGH": "14.2",
    "LOW": "13.4",
    "CLOSEP*": "13.8",
    "YCP*": "13.3",
    "% CHANGE": "3.76",
    "TRADE": "2025",
    "VALUE (mn)": "81.5410",
    "VOLUME": "5883336"
  },
  {
    "#": "188",
    "TRADING CODE": "MONNOAGML",
    "LTP*": "354.8",
    "HIGH": "361.1",
    "LOW": "354",
    "CLOSEP*": "354.8",
    "YCP*": "361",
    "% CHANGE": "-1.72",
    "TRADE": "605",
    "VALUE (mn)": "15.0950",
    "VOLUME": "42256"
  },
  {
    "#": "189",
    "TRADING CODE": "MONNOCERA",
    "LTP*": "95.8",
    "HIGH": "97.8",
    "LOW": "95.4",
    "CLOSEP*": "95.8",
    "YCP*": "96.9",
    "% CHANGE": "-1.14",
    "TRADE": "1397",
    "VALUE (mn)": "36.0350",
    "VOLUME": "374659"
  },
  {
    "#": "190",
    "TRADING CODE": "MONNOFABR",
    "LTP*": "22.4",
    "HIGH": "22.6",
    "LOW": "22.3",
    "CLOSEP*": "22.4",
    "YCP*": "22.4",
    "% CHANGE": "0",
    "TRADE": "584",
    "VALUE (mn)": "17.3750",
    "VOLUME": "775382"
  },
  {
    "#": "191",
    "TRADING CODE": "MONOSPOOL",
    "LTP*": "120",
    "HIGH": "122.7",
    "LOW": "119.6",
    "CLOSEP*": "120",
    "YCP*": "121.9",
    "% CHANGE": "-1.56",
    "TRADE": "1462",
    "VALUE (mn)": "45.1750",
    "VOLUME": "373375"
  },
  {
    "#": "192",
    "TRADING CODE": "MPETROLEUM",
    "LTP*": "215.5",
    "HIGH": "215.8",
    "LOW": "212",
    "CLOSEP*": "215.5",
    "YCP*": "215.9",
    "% CHANGE": "-0.19",
    "TRADE": "181",
    "VALUE (mn)": "3.2450",
    "VOLUME": "15069"
  },
  {
    "#": "193",
    "TRADING CODE": "MTB",
    "LTP*": "13.6",
    "HIGH": "13.9",
    "LOW": "13.6",
    "CLOSEP*": "13.6",
    "YCP*": "13.8",
    "% CHANGE": "-1.45",
    "TRADE": "166",
    "VALUE (mn)": "3.8940",
    "VOLUME": "284372"
  },
  {
    "#": "194",
    "TRADING CODE": "NAHEEACP",
    "LTP*": "37.1",
    "HIGH": "38.2",
    "LOW": "36.9",
    "CLOSEP*": "37.1",
    "YCP*": "37.4",
    "% CHANGE": "-0.80",
    "TRADE": "1015",
    "VALUE (mn)": "29.1120",
    "VOLUME": "775569"
  },
  {
    "#": "195",
    "TRADING CODE": "NATLIFEINS",
    "LTP*": "104.1",
    "HIGH": "107",
    "LOW": "103.6",
    "CLOSEP*": "104.1",
    "YCP*": "106.7",
    "% CHANGE": "-2.44",
    "TRADE": "454",
    "VALUE (mn)": "9.5930",
    "VOLUME": "91524"
  },
  {
    "#": "196",
    "TRADING CODE": "NAVANACNG",
    "LTP*": "22.7",
    "HIGH": "22.7",
    "LOW": "22.6",
    "CLOSEP*": "22.7",
    "YCP*": "22.5",
    "% CHANGE": "0.89",
    "TRADE": "45",
    "VALUE (mn)": "0.7310",
    "VOLUME": "32269"
  },
  {
    "#": "197",
    "TRADING CODE": "NAVANAPHAR",
    "LTP*": "74.1",
    "HIGH": "77.5",
    "LOW": "73.7",
    "CLOSEP*": "74.1",
    "YCP*": "75.1",
    "% CHANGE": "-1.33",
    "TRADE": "2746",
    "VALUE (mn)": "120.0090",
    "VOLUME": "1582200"
  },
  {
    "#": "198",
    "TRADING CODE": "NBL",
    "LTP*": "3.9",
    "HIGH": "3.9",
    "LOW": "3.7",
    "CLOSEP*": "3.8",
    "YCP*": "3.8",
    "% CHANGE": "2.63",
    "TRADE": "288",
    "VALUE (mn)": "6.7600",
    "VOLUME": "1776196"
  },
  {
    "#": "199",
    "TRADING CODE": "NCCBANK",
    "LTP*": "15.5",
    "HIGH": "15.6",
    "LOW": "15.4",
    "CLOSEP*": "15.5",
    "YCP*": "15.6",
    "% CHANGE": "-0.64",
    "TRADE": "944",
    "VALUE (mn)": "54.9830",
    "VOLUME": "3550816"
  },
  {
    "#": "200",
    "TRADING CODE": "NEWLINE",
    "LTP*": "6",
    "HIGH": "6.1",
    "LOW": "5.7",
    "CLOSEP*": "6",
    "YCP*": "5.6",
    "% CHANGE": "7.14",
    "TRADE": "482",
    "VALUE (mn)": "11.2830",
    "VOLUME": "1883119"
  },
  {
    "#": "201",
    "TRADING CODE": "NFML",
    "LTP*": "20.1",
    "HIGH": "20.9",
    "LOW": "20",
    "CLOSEP*": "20.1",
    "YCP*": "20.7",
    "% CHANGE": "-2.90",
    "TRADE": "1455",
    "VALUE (mn)": "42.0480",
    "VOLUME": "2062364"
  },
  {
    "#": "202",
    "TRADING CODE": "NHFIL",
    "LTP*": "31.6",
    "HIGH": "32.4",
    "LOW": "31.3",
    "CLOSEP*": "31.6",
    "YCP*": "31.5",
    "% CHANGE": "0.32",
    "TRADE": "887",
    "VALUE (mn)": "40.4030",
    "VOLUME": "1269261"
  },
  {
    "#": "203",
    "TRADING CODE": "NITOLINS",
    "LTP*": "37",
    "HIGH": "39.4",
    "LOW": "36.9",
    "CLOSEP*": "37",
    "YCP*": "37.6",
    "% CHANGE": "-1.60",
    "TRADE": "382",
    "VALUE (mn)": "13.4390",
    "VOLUME": "353362"
  },
  {
    "#": "204",
    "TRADING CODE": "NORTHRNINS",
    "LTP*": "39.6",
    "HIGH": "42",
    "LOW": "39.3",
    "CLOSEP*": "39.6",
    "YCP*": "41.2",
    "% CHANGE": "-3.88",
    "TRADE": "460",
    "VALUE (mn)": "8.6530",
    "VOLUME": "214354"
  },
  {
    "#": "205",
    "TRADING CODE": "NPOLYMER",
    "LTP*": "34.4",
    "HIGH": "35",
    "LOW": "33.8",
    "CLOSEP*": "34.4",
    "YCP*": "34.7",
    "% CHANGE": "-0.86",
    "TRADE": "592",
    "VALUE (mn)": "16.0160",
    "VOLUME": "463902"
  },
  {
    "#": "206",
    "TRADING CODE": "NRBBANK",
    "LTP*": "6",
    "HIGH": "6.1",
    "LOW": "6",
    "CLOSEP*": "6",
    "YCP*": "6",
    "% CHANGE": "0",
    "TRADE": "106",
    "VALUE (mn)": "2.7040",
    "VOLUME": "450479"
  },
  {
    "#": "207",
    "TRADING CODE": "NRBCBANK",
    "LTP*": "7.6",
    "HIGH": "7.7",
    "LOW": "7.4",
    "CLOSEP*": "7.6",
    "YCP*": "7.4",
    "% CHANGE": "2.70",
    "TRADE": "88",
    "VALUE (mn)": "3.8390",
    "VOLUME": "509429"
  },
  {
    "#": "208",
    "TRADING CODE": "NTC",
    "LTP*": "174.8",
    "HIGH": "179.1",
    "LOW": "173.5",
    "CLOSEP*": "174.8",
    "YCP*": "180.1",
    "% CHANGE": "-2.94",
    "TRADE": "135",
    "VALUE (mn)": "1.7350",
    "VOLUME": "9887"
  },
  {
    "#": "209",
    "TRADING CODE": "NTLTUBES",
    "LTP*": "71",
    "HIGH": "72.8",
    "LOW": "70.5",
    "CLOSEP*": "71",
    "YCP*": "72.4",
    "% CHANGE": "-1.93",
    "TRADE": "706",
    "VALUE (mn)": "16.2310",
    "VOLUME": "227094"
  },
  {
    "#": "210",
    "TRADING CODE": "OAL",
    "LTP*": "6.7",
    "HIGH": "6.8",
    "LOW": "6.6",
    "CLOSEP*": "6.7",
    "YCP*": "6.7",
    "% CHANGE": "0",
    "TRADE": "100",
    "VALUE (mn)": "0.9760",
    "VOLUME": "145771"
  },
  {
    "#": "211",
    "TRADING CODE": "OIMEX",
    "LTP*": "16.8",
    "HIGH": "17",
    "LOW": "16.6",
    "CLOSEP*": "16.8",
    "YCP*": "16.5",
    "% CHANGE": "1.82",
    "TRADE": "295",
    "VALUE (mn)": "5.3620",
    "VOLUME": "318090"
  },
  {
    "#": "212",
    "TRADING CODE": "OLYMPIC",
    "LTP*": "157",
    "HIGH": "160.3",
    "LOW": "156.4",
    "CLOSEP*": "157",
    "YCP*": "159.9",
    "% CHANGE": "-1.81",
    "TRADE": "781",
    "VALUE (mn)": "29.0120",
    "VOLUME": "183568"
  },
  {
    "#": "213",
    "TRADING CODE": "ONEBANKPLC",
    "LTP*": "7.9",
    "HIGH": "8",
    "LOW": "7.8",
    "CLOSEP*": "7.9",
    "YCP*": "7.9",
    "% CHANGE": "0",
    "TRADE": "89",
    "VALUE (mn)": "1.5630",
    "VOLUME": "196292"
  },
  {
    "#": "214",
    "TRADING CODE": "ORIONINFU",
    "LTP*": "295.8",
    "HIGH": "303.7",
    "LOW": "295",
    "CLOSEP*": "295.8",
    "YCP*": "302.9",
    "% CHANGE": "-2.34",
    "TRADE": "2500",
    "VALUE (mn)": "53.2760",
    "VOLUME": "179031"
  },
  {
    "#": "215",
    "TRADING CODE": "ORIONPHARM",
    "LTP*": "29.8",
    "HIGH": "30.2",
    "LOW": "29.7",
    "CLOSEP*": "29.8",
    "YCP*": "29.9",
    "% CHANGE": "-0.33",
    "TRADE": "263",
    "VALUE (mn)": "7.8980",
    "VOLUME": "264792"
  },
  {
    "#": "216",
    "TRADING CODE": "PADMALIFE",
    "LTP*": "18.4",
    "HIGH": "18.8",
    "LOW": "18",
    "CLOSEP*": "18.4",
    "YCP*": "18.4",
    "% CHANGE": "0",
    "TRADE": "54",
    "VALUE (mn)": "0.3870",
    "VOLUME": "21180"
  },
  {
    "#": "217",
    "TRADING CODE": "PADMAOIL",
    "LTP*": "203.6",
    "HIGH": "205.2",
    "LOW": "202.1",
    "CLOSEP*": "203.6",
    "YCP*": "204.9",
    "% CHANGE": "-0.63",
    "TRADE": "284",
    "VALUE (mn)": "10.1930",
    "VOLUME": "50031"
  },
  {
    "#": "218",
    "TRADING CODE": "PARAMOUNT",
    "LTP*": "62.7",
    "HIGH": "66.9",
    "LOW": "62",
    "CLOSEP*": "62.7",
    "YCP*": "64.9",
    "% CHANGE": "-3.39",
    "TRADE": "1436",
    "VALUE (mn)": "47.0790",
    "VOLUME": "724823"
  },
  {
    "#": "219",
    "TRADING CODE": "PDL",
    "LTP*": "5.6",
    "HIGH": "5.6",
    "LOW": "5.4",
    "CLOSEP*": "5.5",
    "YCP*": "5.4",
    "% CHANGE": "3.70",
    "TRADE": "134",
    "VALUE (mn)": "2.3990",
    "VOLUME": "432683"
  },
  {
    "#": "220",
    "TRADING CODE": "PENINSULA",
    "LTP*": "25.4",
    "HIGH": "26",
    "LOW": "25.3",
    "CLOSEP*": "25.4",
    "YCP*": "25.7",
    "% CHANGE": "-1.17",
    "TRADE": "761",
    "VALUE (mn)": "24.0950",
    "VOLUME": "938183"
  },
  {
    "#": "221",
    "TRADING CODE": "PEOPLESINS",
    "LTP*": "57",
    "HIGH": "61.4",
    "LOW": "56.7",
    "CLOSEP*": "57.4",
    "YCP*": "60.9",
    "% CHANGE": "-6.40",
    "TRADE": "883",
    "VALUE (mn)": "35.9580",
    "VOLUME": "612594"
  },
  {
    "#": "222",
    "TRADING CODE": "PHARMAID",
    "LTP*": "630.7",
    "HIGH": "658.3",
    "LOW": "627.4",
    "CLOSEP*": "630.7",
    "YCP*": "644.7",
    "% CHANGE": "-2.17",
    "TRADE": "1426",
    "VALUE (mn)": "43.7920",
    "VOLUME": "68166"
  },
  {
    "#": "223",
    "TRADING CODE": "PHENIXINS",
    "LTP*": "44",
    "HIGH": "46.6",
    "LOW": "43",
    "CLOSEP*": "44",
    "YCP*": "45.6",
    "% CHANGE": "-3.51",
    "TRADE": "728",
    "VALUE (mn)": "25.7140",
    "VOLUME": "569033"
  },
  {
    "#": "224",
    "TRADING CODE": "PIONEERINS",
    "LTP*": "67.8",
    "HIGH": "70.9",
    "LOW": "66.8",
    "CLOSEP*": "67.8",
    "YCP*": "70.7",
    "% CHANGE": "-4.10",
    "TRADE": "757",
    "VALUE (mn)": "33.2180",
    "VOLUME": "480282"
  },
  {
    "#": "225",
    "TRADING CODE": "PLFSL",
    "LTP*": "1.4",
    "HIGH": "1.4",
    "LOW": "1.4",
    "CLOSEP*": "1.4",
    "YCP*": "1.3",
    "% CHANGE": "7.69",
    "TRADE": "204",
    "VALUE (mn)": "3.8630",
    "VOLUME": "2759095"
  },
  {
    "#": "226",
    "TRADING CODE": "POPULARLIF",
    "LTP*": "63.9",
    "HIGH": "64.6",
    "LOW": "63.5",
    "CLOSEP*": "63.9",
    "YCP*": "63.9",
    "% CHANGE": "0",
    "TRADE": "1112",
    "VALUE (mn)": "48.3410",
    "VOLUME": "756939"
  },
  {
    "#": "227",
    "TRADING CODE": "POWERGRID",
    "LTP*": "40.7",
    "HIGH": "41.9",
    "LOW": "40.6",
    "CLOSEP*": "40.7",
    "YCP*": "41.5",
    "% CHANGE": "-1.93",
    "TRADE": "470",
    "VALUE (mn)": "8.7390",
    "VOLUME": "213451"
  },
  {
    "#": "228",
    "TRADING CODE": "PRAGATIINS",
    "LTP*": "78.6",
    "HIGH": "82.6",
    "LOW": "78.1",
    "CLOSEP*": "78.6",
    "YCP*": "81.5",
    "% CHANGE": "-3.56",
    "TRADE": "689",
    "VALUE (mn)": "15.0390",
    "VOLUME": "188654"
  },
  {
    "#": "229",
    "TRADING CODE": "PRAGATILIF",
    "LTP*": "173.7",
    "HIGH": "178.4",
    "LOW": "172.5",
    "CLOSEP*": "173.7",
    "YCP*": "178.1",
    "% CHANGE": "-2.47",
    "TRADE": "1207",
    "VALUE (mn)": "34.3080",
    "VOLUME": "195603"
  },
  {
    "#": "230",
    "TRADING CODE": "PREMIERBAN",
    "LTP*": "5.5",
    "HIGH": "5.6",
    "LOW": "5.2",
    "CLOSEP*": "5.5",
    "YCP*": "5.3",
    "% CHANGE": "3.77",
    "TRADE": "402",
    "VALUE (mn)": "7.9430",
    "VOLUME": "1472173"
  },
  {
    "#": "231",
    "TRADING CODE": "PREMIERCEM",
    "LTP*": "51.1",
    "HIGH": "52",
    "LOW": "51",
    "CLOSEP*": "51.1",
    "YCP*": "51.5",
    "% CHANGE": "-0.78",
    "TRADE": "628",
    "VALUE (mn)": "21.6220",
    "VOLUME": "421482"
  },
  {
    "#": "232",
    "TRADING CODE": "PRIMEBANK",
    "LTP*": "30.4",
    "HIGH": "30.7",
    "LOW": "30.4",
    "CLOSEP*": "30.4",
    "YCP*": "30.5",
    "% CHANGE": "-0.33",
    "TRADE": "219",
    "VALUE (mn)": "14.1230",
    "VOLUME": "463278"
  },
  {
    "#": "233",
    "TRADING CODE": "PRIMEINSUR",
    "LTP*": "47.8",
    "HIGH": "49.8",
    "LOW": "47.2",
    "CLOSEP*": "47.8",
    "YCP*": "48.5",
    "% CHANGE": "-1.44",
    "TRADE": "434",
    "VALUE (mn)": "16.2160",
    "VOLUME": "337117"
  },
  {
    "#": "234",
    "TRADING CODE": "PRIMELIFE",
    "LTP*": "41.5",
    "HIGH": "44.1",
    "LOW": "41.2",
    "CLOSEP*": "41.5",
    "YCP*": "43.5",
    "% CHANGE": "-4.60",
    "TRADE": "299",
    "VALUE (mn)": "6.9630",
    "VOLUME": "165130"
  },
  {
    "#": "235",
    "TRADING CODE": "PROGRESLIF",
    "LTP*": "41.9",
    "HIGH": "42.6",
    "LOW": "41.2",
    "CLOSEP*": "41.4",
    "YCP*": "42.4",
    "% CHANGE": "-1.18",
    "TRADE": "95",
    "VALUE (mn)": "1.0360",
    "VOLUME": "24756"
  },
  {
    "#": "236",
    "TRADING CODE": "PROVATIINS",
    "LTP*": "60.9",
    "HIGH": "63.2",
    "LOW": "60.3",
    "CLOSEP*": "60.9",
    "YCP*": "63",
    "% CHANGE": "-3.33",
    "TRADE": "1076",
    "VALUE (mn)": "42.1250",
    "VOLUME": "680090"
  },
  {
    "#": "237",
    "TRADING CODE": "PTL",
    "LTP*": "64",
    "HIGH": "65.6",
    "LOW": "63.8",
    "CLOSEP*": "64",
    "YCP*": "64.9",
    "% CHANGE": "-1.39",
    "TRADE": "550",
    "VALUE (mn)": "20.2390",
    "VOLUME": "312940"
  },
  {
    "#": "238",
    "TRADING CODE": "PUBALIBANK",
    "LTP*": "37",
    "HIGH": "37.4",
    "LOW": "36.8",
    "CLOSEP*": "37",
    "YCP*": "37.3",
    "% CHANGE": "-0.80",
    "TRADE": "347",
    "VALUE (mn)": "9.9220",
    "VOLUME": "268124"
  },
  {
    "#": "239",
    "TRADING CODE": "PURABIGEN",
    "LTP*": "32.3",
    "HIGH": "34",
    "LOW": "31.9",
    "CLOSEP*": "32.3",
    "YCP*": "33.6",
    "% CHANGE": "-3.87",
    "TRADE": "794",
    "VALUE (mn)": "26.0780",
    "VOLUME": "791279"
  },
  {
    "#": "240",
    "TRADING CODE": "QUASEMIND",
    "LTP*": "45.5",
    "HIGH": "50.4",
    "LOW": "45.4",
    "CLOSEP*": "45.5",
    "YCP*": "45.9",
    "% CHANGE": "-0.87",
    "TRADE": "561",
    "VALUE (mn)": "20.8770",
    "VOLUME": "455849"
  },
  {
    "#": "241",
    "TRADING CODE": "QUEENSOUTH",
    "LTP*": "15.7",
    "HIGH": "16",
    "LOW": "15.7",
    "CLOSEP*": "15.7",
    "YCP*": "15.8",
    "% CHANGE": "-0.63",
    "TRADE": "479",
    "VALUE (mn)": "13.4260",
    "VOLUME": "851861"
  },
  {
    "#": "242",
    "TRADING CODE": "RAHIMAFOOD",
    "LTP*": "92.8",
    "HIGH": "97",
    "LOW": "92.1",
    "CLOSEP*": "92.8",
    "YCP*": "95.5",
    "% CHANGE": "-2.83",
    "TRADE": "427",
    "VALUE (mn)": "4.5570",
    "VOLUME": "48828"
  },
  {
    "#": "243",
    "TRADING CODE": "RAHIMTEXT",
    "LTP*": "217.3",
    "HIGH": "220.1",
    "LOW": "216.1",
    "CLOSEP*": "217.3",
    "YCP*": "218.1",
    "% CHANGE": "-0.37",
    "TRADE": "447",
    "VALUE (mn)": "7.3800",
    "VOLUME": "33899"
  },
  {
    "#": "244",
    "TRADING CODE": "RAKCERAMIC",
    "LTP*": "32.2",
    "HIGH": "32.8",
    "LOW": "31.5",
    "CLOSEP*": "32.2",
    "YCP*": "31.4",
    "% CHANGE": "2.55",
    "TRADE": "1291",
    "VALUE (mn)": "44.1030",
    "VOLUME": "1371597"
  },
  {
    "#": "245",
    "TRADING CODE": "RANFOUNDRY",
    "LTP*": "166.5",
    "HIGH": "175.9",
    "LOW": "165.1",
    "CLOSEP*": "166.5",
    "YCP*": "169",
    "% CHANGE": "-1.48",
    "TRADE": "265",
    "VALUE (mn)": "4.0690",
    "VOLUME": "24239"
  },
  {
    "#": "246",
    "TRADING CODE": "RDFOOD",
    "LTP*": "27.9",
    "HIGH": "29.1",
    "LOW": "27.5",
    "CLOSEP*": "27.9",
    "YCP*": "28.9",
    "% CHANGE": "-3.46",
    "TRADE": "1797",
    "VALUE (mn)": "45.8030",
    "VOLUME": "1618762"
  },
  {
    "#": "247",
    "TRADING CODE": "RECKITTBEN",
    "LTP*": "3325.4",
    "HIGH": "3339.5",
    "LOW": "3325",
    "CLOSEP*": "3325.4",
    "YCP*": "3324.8",
    "% CHANGE": "0.02",
    "TRADE": "66",
    "VALUE (mn)": "0.8060",
    "VOLUME": "242"
  },
  {
    "#": "248",
    "TRADING CODE": "RELIANCINS",
    "LTP*": "108.8",
    "HIGH": "113.9",
    "LOW": "105.5",
    "CLOSEP*": "108.8",
    "YCP*": "114.1",
    "% CHANGE": "-4.65",
    "TRADE": "409",
    "VALUE (mn)": "18.2600",
    "VOLUME": "165978"
  },
  {
    "#": "249",
    "TRADING CODE": "RENATA",
    "LTP*": "474.9",
    "HIGH": "478",
    "LOW": "473.6",
    "CLOSEP*": "474.9",
    "YCP*": "475.9",
    "% CHANGE": "-0.21",
    "TRADE": "1072",
    "VALUE (mn)": "31.6880",
    "VOLUME": "66659"
  },
  {
    "#": "250",
    "TRADING CODE": "REPUBLIC",
    "LTP*": "37.5",
    "HIGH": "39.6",
    "LOW": "37.3",
    "CLOSEP*": "37.5",
    "YCP*": "39.2",
    "% CHANGE": "-4.34",
    "TRADE": "501",
    "VALUE (mn)": "14.1060",
    "VOLUME": "369187"
  },
  {
    "#": "251",
    "TRADING CODE": "RINGSHINE",
    "LTP*": "3.9",
    "HIGH": "3.9",
    "LOW": "3.8",
    "CLOSEP*": "3.8",
    "YCP*": "3.9",
    "% CHANGE": "0",
    "TRADE": "167",
    "VALUE (mn)": "2.8940",
    "VOLUME": "755298"
  },
  {
    "#": "252",
    "TRADING CODE": "ROBI",
    "LTP*": "32.6",
    "HIGH": "33.2",
    "LOW": "32.4",
    "CLOSEP*": "32.6",
    "YCP*": "33",
    "% CHANGE": "-1.21",
    "TRADE": "1978",
    "VALUE (mn)": "85.7980",
    "VOLUME": "2621462"
  },
  {
    "#": "253",
    "TRADING CODE": "RUNNERAUTO",
    "LTP*": "41.8",
    "HIGH": "42.3",
    "LOW": "41.4",
    "CLOSEP*": "41.8",
    "YCP*": "41.6",
    "% CHANGE": "0.48",
    "TRADE": "434",
    "VALUE (mn)": "15.3240",
    "VOLUME": "366261"
  },
  {
    "#": "254",
    "TRADING CODE": "RUPALIBANK",
    "LTP*": "17.8",
    "HIGH": "18.3",
    "LOW": "17.8",
    "CLOSEP*": "17.8",
    "YCP*": "18.3",
    "% CHANGE": "-2.73",
    "TRADE": "187",
    "VALUE (mn)": "4.5240",
    "VOLUME": "252307"
  },
  {
    "#": "255",
    "TRADING CODE": "RUPALIINS",
    "LTP*": "29.6",
    "HIGH": "31.4",
    "LOW": "29.4",
    "CLOSEP*": "29.6",
    "YCP*": "30.9",
    "% CHANGE": "-4.21",
    "TRADE": "615",
    "VALUE (mn)": "18.7700",
    "VOLUME": "623415"
  },
  {
    "#": "256",
    "TRADING CODE": "RUPALILIFE",
    "LTP*": "92.8",
    "HIGH": "95",
    "LOW": "92.1",
    "CLOSEP*": "92.8",
    "YCP*": "93.6",
    "% CHANGE": "-0.85",
    "TRADE": "789",
    "VALUE (mn)": "24.4130",
    "VOLUME": "261142"
  },
  {
    "#": "257",
    "TRADING CODE": "SAFKOSPINN",
    "LTP*": "21",
    "HIGH": "21.2",
    "LOW": "20.4",
    "CLOSEP*": "20.9",
    "YCP*": "20.7",
    "% CHANGE": "1.45",
    "TRADE": "76",
    "VALUE (mn)": "0.1950",
    "VOLUME": "9445"
  },
  {
    "#": "258",
    "TRADING CODE": "SAIFPOWER",
    "LTP*": "9.8",
    "HIGH": "10.1",
    "LOW": "9.4",
    "CLOSEP*": "9.8",
    "YCP*": "9.4",
    "% CHANGE": "4.26",
    "TRADE": "438",
    "VALUE (mn)": "7.8740",
    "VOLUME": "799176"
  },
  {
    "#": "259",
    "TRADING CODE": "SAIHAMCOT",
    "LTP*": "20.4",
    "HIGH": "20.6",
    "LOW": "20.2",
    "CLOSEP*": "20.4",
    "YCP*": "20.4",
    "% CHANGE": "0",
    "TRADE": "592",
    "VALUE (mn)": "39.3170",
    "VOLUME": "1925007"
  },
  {
    "#": "260",
    "TRADING CODE": "SAIHAMTEX",
    "LTP*": "19.2",
    "HIGH": "19.6",
    "LOW": "19.1",
    "CLOSEP*": "19.2",
    "YCP*": "19.4",
    "% CHANGE": "-1.03",
    "TRADE": "420",
    "VALUE (mn)": "12.1890",
    "VOLUME": "631580"
  },
  {
    "#": "261",
    "TRADING CODE": "SALAMCRST",
    "LTP*": "14",
    "HIGH": "14.3",
    "LOW": "13.9",
    "CLOSEP*": "14",
    "YCP*": "14.1",
    "% CHANGE": "-0.71",
    "TRADE": "154",
    "VALUE (mn)": "2.4820",
    "VOLUME": "177282"
  },
  {
    "#": "262",
    "TRADING CODE": "SALVO",
    "LTP*": "38.5",
    "HIGH": "39.4",
    "LOW": "38.4",
    "CLOSEP*": "38.5",
    "YCP*": "38.6",
    "% CHANGE": "-0.26",
    "TRADE": "1681",
    "VALUE (mn)": "67.5570",
    "VOLUME": "1736215"
  },
  {
    "#": "263",
    "TRADING CODE": "SAMATALETH",
    "LTP*": "100.4",
    "HIGH": "104.7",
    "LOW": "100",
    "CLOSEP*": "100.4",
    "YCP*": "102.5",
    "% CHANGE": "-2.05",
    "TRADE": "305",
    "VALUE (mn)": "4.5510",
    "VOLUME": "44644"
  },
  {
    "#": "264",
    "TRADING CODE": "SAMORITA",
    "LTP*": "93",
    "HIGH": "95",
    "LOW": "92.1",
    "CLOSEP*": "92.7",
    "YCP*": "94.1",
    "% CHANGE": "-1.17",
    "TRADE": "553",
    "VALUE (mn)": "13.1560",
    "VOLUME": "141712"
  },
  {
    "#": "265",
    "TRADING CODE": "SANDHANINS",
    "LTP*": "28",
    "HIGH": "28.7",
    "LOW": "27.9",
    "CLOSEP*": "28",
    "YCP*": "28.2",
    "% CHANGE": "-0.71",
    "TRADE": "578",
    "VALUE (mn)": "14.0020",
    "VOLUME": "496044"
  },
  {
    "#": "266",
    "TRADING CODE": "SAPORTL",
    "LTP*": "51.4",
    "HIGH": "53.7",
    "LOW": "51.2",
    "CLOSEP*": "51.4",
    "YCP*": "53.2",
    "% CHANGE": "-3.38",
    "TRADE": "2632",
    "VALUE (mn)": "172.9020",
    "VOLUME": "3337527"
  },
  {
    "#": "267",
    "TRADING CODE": "SBACBANK",
    "LTP*": "6.5",
    "HIGH": "6.7",
    "LOW": "6.5",
    "CLOSEP*": "6.6",
    "YCP*": "6.5",
    "% CHANGE": "0",
    "TRADE": "100",
    "VALUE (mn)": "1.9050",
    "VOLUME": "288972"
  },
  {
    "#": "268",
    "TRADING CODE": "SEAPEARL",
    "LTP*": "41.9",
    "HIGH": "43.6",
    "LOW": "41.6",
    "CLOSEP*": "41.9",
    "YCP*": "43",
    "% CHANGE": "-2.56",
    "TRADE": "2076",
    "VALUE (mn)": "76.0630",
    "VOLUME": "1780770"
  },
  {
    "#": "269",
    "TRADING CODE": "SHAHJABANK",
    "LTP*": "17.6",
    "HIGH": "17.7",
    "LOW": "17.5",
    "CLOSEP*": "17.6",
    "YCP*": "17.7",
    "% CHANGE": "-0.56",
    "TRADE": "86",
    "VALUE (mn)": "1.8160",
    "VOLUME": "103200"
  },
  {
    "#": "270",
    "TRADING CODE": "SHARPIND",
    "LTP*": "33.4",
    "HIGH": "34.1",
    "LOW": "32",
    "CLOSEP*": "33.4",
    "YCP*": "31.8",
    "% CHANGE": "5.03",
    "TRADE": "2618",
    "VALUE (mn)": "236.7860",
    "VOLUME": "7191196"
  },
  {
    "#": "271",
    "TRADING CODE": "SHASHADNIM",
    "LTP*": "27.6",
    "HIGH": "27.9",
    "LOW": "27.2",
    "CLOSEP*": "27.6",
    "YCP*": "27.1",
    "% CHANGE": "1.85",
    "TRADE": "799",
    "VALUE (mn)": "48.3890",
    "VOLUME": "1748447"
  },
  {
    "#": "272",
    "TRADING CODE": "SHEPHERD",
    "LTP*": "16.6",
    "HIGH": "16.8",
    "LOW": "16.4",
    "CLOSEP*": "16.6",
    "YCP*": "16.5",
    "% CHANGE": "0.61",
    "TRADE": "580",
    "VALUE (mn)": "20.3740",
    "VOLUME": "1227009"
  },
  {
    "#": "273",
    "TRADING CODE": "SHYAMPSUG",
    "LTP*": "325.3",
    "HIGH": "326",
    "LOW": "310",
    "CLOSEP*": "325.3",
    "YCP*": "318.6",
    "% CHANGE": "2.10",
    "TRADE": "410",
    "VALUE (mn)": "12.1100",
    "VOLUME": "37599"
  },
  {
    "#": "274",
    "TRADING CODE": "SICL",
    "LTP*": "38.8",
    "HIGH": "41.7",
    "LOW": "38.7",
    "CLOSEP*": "38.8",
    "YCP*": "41.3",
    "% CHANGE": "-6.05",
    "TRADE": "1280",
    "VALUE (mn)": "41.3140",
    "VOLUME": "1039699"
  },
  {
    "#": "275",
    "TRADING CODE": "SILCOPHL",
    "LTP*": "22.7",
    "HIGH": "23.3",
    "LOW": "22.3",
    "CLOSEP*": "22.7",
    "YCP*": "22.3",
    "% CHANGE": "1.79",
    "TRADE": "3178",
    "VALUE (mn)": "145.6390",
    "VOLUME": "6385543"
  },
  {
    "#": "276",
    "TRADING CODE": "SILVAPHL",
    "LTP*": "17.3",
    "HIGH": "17.8",
    "LOW": "17.2",
    "CLOSEP*": "17.3",
    "YCP*": "17.3",
    "% CHANGE": "0",
    "TRADE": "1622",
    "VALUE (mn)": "68.6770",
    "VOLUME": "3944356"
  },
  {
    "#": "277",
    "TRADING CODE": "SIMTEX",
    "LTP*": "27.7",
    "HIGH": "28.3",
    "LOW": "27.6",
    "CLOSEP*": "27.7",
    "YCP*": "27.8",
    "% CHANGE": "-0.36",
    "TRADE": "1094",
    "VALUE (mn)": "38.0410",
    "VOLUME": "1362740"
  },
  {
    "#": "278",
    "TRADING CODE": "SINGERBD",
    "LTP*": "76.7",
    "HIGH": "77.9",
    "LOW": "76.5",
    "CLOSEP*": "76.7",
    "YCP*": "77",
    "% CHANGE": "-0.39",
    "TRADE": "212",
    "VALUE (mn)": "1.9230",
    "VOLUME": "24863"
  },
  {
    "#": "279",
    "TRADING CODE": "SINOBANGLA",
    "LTP*": "58.2",
    "HIGH": "59.5",
    "LOW": "58",
    "CLOSEP*": "58.2",
    "YCP*": "59.4",
    "% CHANGE": "-2.02",
    "TRADE": "1399",
    "VALUE (mn)": "39.6790",
    "VOLUME": "676683"
  },
  {
    "#": "280",
    "TRADING CODE": "SIPLC",
    "LTP*": "107.7",
    "HIGH": "109.5",
    "LOW": "102.5",
    "CLOSEP*": "107.7",
    "YCP*": "108.4",
    "% CHANGE": "-0.65",
    "TRADE": "449",
    "VALUE (mn)": "45.7400",
    "VOLUME": "430253"
  },
  {
    "#": "281",
    "TRADING CODE": "SKTRIMS",
    "LTP*": "13.9",
    "HIGH": "14.3",
    "LOW": "13.7",
    "CLOSEP*": "13.9",
    "YCP*": "13.8",
    "% CHANGE": "0.72",
    "TRADE": "307",
    "VALUE (mn)": "3.9280",
    "VOLUME": "280616"
  },
  {
    "#": "282",
    "TRADING CODE": "SONALIANSH",
    "LTP*": "216",
    "HIGH": "223.5",
    "LOW": "215.3",
    "CLOSEP*": "216",
    "YCP*": "219.9",
    "% CHANGE": "-1.77",
    "TRADE": "1489",
    "VALUE (mn)": "30.8690",
    "VOLUME": "141136"
  },
  {
    "#": "283",
    "TRADING CODE": "SONALILIFE",
    "LTP*": "84.2",
    "HIGH": "85.9",
    "LOW": "84.1",
    "CLOSEP*": "84.2",
    "YCP*": "84.9",
    "% CHANGE": "-0.82",
    "TRADE": "985",
    "VALUE (mn)": "63.5220",
    "VOLUME": "750700"
  },
  {
    "#": "284",
    "TRADING CODE": "SONALIPAPR",
    "LTP*": "249.4",
    "HIGH": "257.8",
    "LOW": "245.6",
    "CLOSEP*": "249.4",
    "YCP*": "245.7",
    "% CHANGE": "1.51",
    "TRADE": "2535",
    "VALUE (mn)": "79.7300",
    "VOLUME": "315584"
  },
  {
    "#": "285",
    "TRADING CODE": "SONARBAINS",
    "LTP*": "41.7",
    "HIGH": "44",
    "LOW": "41.1",
    "CLOSEP*": "41.7",
    "YCP*": "43.5",
    "% CHANGE": "-4.14",
    "TRADE": "892",
    "VALUE (mn)": "21.6170",
    "VOLUME": "509247"
  },
  {
    "#": "286",
    "TRADING CODE": "SONARGAON",
    "LTP*": "82.6",
    "HIGH": "88.9",
    "LOW": "81",
    "CLOSEP*": "82.6",
    "YCP*": "86.7",
    "% CHANGE": "-4.73",
    "TRADE": "997",
    "VALUE (mn)": "16.8570",
    "VOLUME": "198381"
  },
  {
    "#": "287",
    "TRADING CODE": "SOUTHEASTB",
    "LTP*": "10.2",
    "HIGH": "10.3",
    "LOW": "10.1",
    "CLOSEP*": "10.2",
    "YCP*": "10.2",
    "% CHANGE": "0",
    "TRADE": "144",
    "VALUE (mn)": "6.0980",
    "VOLUME": "598949"
  },
  {
    "#": "288",
    "TRADING CODE": "SPCERAMICS",
    "LTP*": "23.9",
    "HIGH": "24.5",
    "LOW": "23.8",
    "CLOSEP*": "23.9",
    "YCP*": "24.2",
    "% CHANGE": "-1.24",
    "TRADE": "864",
    "VALUE (mn)": "31.8030",
    "VOLUME": "1323680"
  },
  {
    "#": "289",
    "TRADING CODE": "SPCL",
    "LTP*": "57.2",
    "HIGH": "58.6",
    "LOW": "56.9",
    "CLOSEP*": "57.2",
    "YCP*": "58.3",
    "% CHANGE": "-1.89",
    "TRADE": "1052",
    "VALUE (mn)": "38.2820",
    "VOLUME": "661458"
  },
  {
    "#": "290",
    "TRADING CODE": "SQUARETEXT",
    "LTP*": "51",
    "HIGH": "52",
    "LOW": "50.8",
    "CLOSEP*": "51",
    "YCP*": "51.3",
    "% CHANGE": "-0.58",
    "TRADE": "160",
    "VALUE (mn)": "2.5120",
    "VOLUME": "49208"
  },
  {
    "#": "291",
    "TRADING CODE": "SQURPHARMA",
    "LTP*": "223.5",
    "HIGH": "225.5",
    "LOW": "223.1",
    "CLOSEP*": "223.5",
    "YCP*": "225",
    "% CHANGE": "-0.67",
    "TRADE": "1549",
    "VALUE (mn)": "48.1710",
    "VOLUME": "215349"
  },
  {
    "#": "292",
    "TRADING CODE": "SSSTEEL",
    "LTP*": "7.2",
    "HIGH": "7.3",
    "LOW": "7.1",
    "CLOSEP*": "7.2",
    "YCP*": "7.2",
    "% CHANGE": "0",
    "TRADE": "346",
    "VALUE (mn)": "8.5850",
    "VOLUME": "1191026"
  },
  {
    "#": "293",
    "TRADING CODE": "STANCERAM",
    "LTP*": "74",
    "HIGH": "76.3",
    "LOW": "73.7",
    "CLOSEP*": "74",
    "YCP*": "74.3",
    "% CHANGE": "-0.40",
    "TRADE": "51",
    "VALUE (mn)": "0.5200",
    "VOLUME": "6972"
  },
  {
    "#": "294",
    "TRADING CODE": "STANDARINS",
    "LTP*": "51.6",
    "HIGH": "53.7",
    "LOW": "51",
    "CLOSEP*": "51.6",
    "YCP*": "53.3",
    "% CHANGE": "-3.19",
    "TRADE": "463",
    "VALUE (mn)": "13.1110",
    "VOLUME": "251465"
  },
  {
    "#": "295",
    "TRADING CODE": "STANDBANKL",
    "LTP*": "4.8",
    "HIGH": "4.9",
    "LOW": "4.8",
    "CLOSEP*": "4.8",
    "YCP*": "4.8",
    "% CHANGE": "0",
    "TRADE": "81",
    "VALUE (mn)": "1.3400",
    "VOLUME": "277149"
  },
  {
    "#": "296",
    "TRADING CODE": "STYLECRAFT",
    "LTP*": "61.3",
    "HIGH": "63",
    "LOW": "61",
    "CLOSEP*": "61.3",
    "YCP*": "62.6",
    "% CHANGE": "-2.08",
    "TRADE": "179",
    "VALUE (mn)": "2.6420",
    "VOLUME": "42986"
  },
  {
    "#": "297",
    "TRADING CODE": "SUMITPOWER",
    "LTP*": "17",
    "HIGH": "17.6",
    "LOW": "16.9",
    "CLOSEP*": "17",
    "YCP*": "17",
    "% CHANGE": "0",
    "TRADE": "979",
    "VALUE (mn)": "27.6760",
    "VOLUME": "1613515"
  },
  {
    "#": "298",
    "TRADING CODE": "SUNLIFEINS",
    "LTP*": "67.6",
    "HIGH": "70",
    "LOW": "67.2",
    "CLOSEP*": "67.6",
    "YCP*": "69.2",
    "% CHANGE": "-2.31",
    "TRADE": "1175",
    "VALUE (mn)": "31.3720",
    "VOLUME": "461068"
  },
  {
    "#": "299",
    "TRADING CODE": "TAKAFULINS",
    "LTP*": "49.6",
    "HIGH": "50.2",
    "LOW": "48.8",
    "CLOSEP*": "49.6",
    "YCP*": "49.9",
    "% CHANGE": "-0.60",
    "TRADE": "551",
    "VALUE (mn)": "10.4760",
    "VOLUME": "211896"
  },
  {
    "#": "300",
    "TRADING CODE": "TAMIJTEX",
    "LTP*": "134.2",
    "HIGH": "137.5",
    "LOW": "133.5",
    "CLOSEP*": "134.2",
    "YCP*": "135",
    "% CHANGE": "-0.59",
    "TRADE": "859",
    "VALUE (mn)": "17.4670",
    "VOLUME": "129559"
  },
  {
    "#": "301",
    "TRADING CODE": "TECHNODRUG",
    "LTP*": "48.5",
    "HIGH": "49.4",
    "LOW": "47.5",
    "CLOSEP*": "48.5",
    "YCP*": "46.9",
    "% CHANGE": "3.41",
    "TRADE": "4819",
    "VALUE (mn)": "247.2650",
    "VOLUME": "5089943"
  },
  {
    "#": "302",
    "TRADING CODE": "TILIL",
    "LTP*": "53.1",
    "HIGH": "54.8",
    "LOW": "53",
    "CLOSEP*": "53.1",
    "YCP*": "54.7",
    "% CHANGE": "-2.93",
    "TRADE": "860",
    "VALUE (mn)": "19.3700",
    "VOLUME": "360680"
  },
  {
    "#": "303",
    "TRADING CODE": "TITASGAS",
    "LTP*": "20.5",
    "HIGH": "20.9",
    "LOW": "20.4",
    "CLOSEP*": "20.5",
    "YCP*": "20.6",
    "% CHANGE": "-0.49",
    "TRADE": "640",
    "VALUE (mn)": "17.1220",
    "VOLUME": "831370"
  },
  {
    "#": "304",
    "TRADING CODE": "TOSRIFA",
    "LTP*": "23.4",
    "HIGH": "24.4",
    "LOW": "23.2",
    "CLOSEP*": "23.4",
    "YCP*": "23.1",
    "% CHANGE": "1.30",
    "TRADE": "766",
    "VALUE (mn)": "22.0770",
    "VOLUME": "926800"
  },
  {
    "#": "305",
    "TRADING CODE": "TRUSTBANK",
    "LTP*": "15.8",
    "HIGH": "16",
    "LOW": "15.7",
    "CLOSEP*": "15.8",
    "YCP*": "15.9",
    "% CHANGE": "-0.63",
    "TRADE": "782",
    "VALUE (mn)": "40.1830",
    "VOLUME": "2540115"
  },
  {
    "#": "306",
    "TRADING CODE": "UCB",
    "LTP*": "9.2",
    "HIGH": "9.3",
    "LOW": "9.1",
    "CLOSEP*": "9.2",
    "YCP*": "9.2",
    "% CHANGE": "0",
    "TRADE": "149",
    "VALUE (mn)": "3.6450",
    "VOLUME": "396067"
  },
  {
    "#": "307",
    "TRADING CODE": "UNIONINS",
    "LTP*": "53.1",
    "HIGH": "57",
    "LOW": "52.1",
    "CLOSEP*": "53.1",
    "YCP*": "54.5",
    "% CHANGE": "-2.57",
    "TRADE": "1361",
    "VALUE (mn)": "62.5280",
    "VOLUME": "1154931"
  },
  {
    "#": "308",
    "TRADING CODE": "UNIQUEHRL",
    "LTP*": "45.8",
    "HIGH": "46.7",
    "LOW": "45.6",
    "CLOSEP*": "45.8",
    "YCP*": "46",
    "% CHANGE": "-0.43",
    "TRADE": "852",
    "VALUE (mn)": "29.4380",
    "VOLUME": "638524"
  },
  {
    "#": "309",
    "TRADING CODE": "UNITEDFIN",
    "LTP*": "16.7",
    "HIGH": "16.9",
    "LOW": "16.2",
    "CLOSEP*": "16.7",
    "YCP*": "16.2",
    "% CHANGE": "3.09",
    "TRADE": "813",
    "VALUE (mn)": "25.6110",
    "VOLUME": "1538492"
  },
  {
    "#": "310",
    "TRADING CODE": "UNITEDINS",
    "LTP*": "52.6",
    "HIGH": "52.6",
    "LOW": "52.1",
    "CLOSEP*": "52.6",
    "YCP*": "47.9",
    "% CHANGE": "9.81",
    "TRADE": "891",
    "VALUE (mn)": "78.4100",
    "VOLUME": "1491245"
  },
  {
    "#": "311",
    "TRADING CODE": "UPGDCL",
    "LTP*": "127.7",
    "HIGH": "129.9",
    "LOW": "127.6",
    "CLOSEP*": "127.7",
    "YCP*": "128.6",
    "% CHANGE": "-0.70",
    "TRADE": "476",
    "VALUE (mn)": "7.3110",
    "VOLUME": "57008"
  },
  {
    "#": "312",
    "TRADING CODE": "UTTARABANK",
    "LTP*": "21.3",
    "HIGH": "21.4",
    "LOW": "21.2",
    "CLOSEP*": "21.3",
    "YCP*": "21.4",
    "% CHANGE": "-0.47",
    "TRADE": "757",
    "VALUE (mn)": "39.3020",
    "VOLUME": "1843782"
  },
  {
    "#": "313",
    "TRADING CODE": "VFSTDL",
    "LTP*": "16.3",
    "HIGH": "16.6",
    "LOW": "16.2",
    "CLOSEP*": "16.3",
    "YCP*": "16.4",
    "% CHANGE": "-0.61",
    "TRADE": "622",
    "VALUE (mn)": "21.7130",
    "VOLUME": "1325348"
  },
  {
    "#": "314",
    "TRADING CODE": "WALTONHIL",
    "LTP*": "395.8",
    "HIGH": "406",
    "LOW": "394",
    "CLOSEP*": "395.8",
    "YCP*": "404.5",
    "% CHANGE": "-2.15",
    "TRADE": "1186",
    "VALUE (mn)": "19.8820",
    "VOLUME": "49845"
  },
  {
    "#": "315",
    "TRADING CODE": "WATACHEM",
    "LTP*": "143.4",
    "HIGH": "146.2",
    "LOW": "142.5",
    "CLOSEP*": "143.4",
    "YCP*": "146.1",
    "% CHANGE": "-1.85",
    "TRADE": "304",
    "VALUE (mn)": "5.7980",
    "VOLUME": "40229"
  },
  {
    "#": "316",
    "TRADING CODE": "WMSHIPYARD",
    "LTP*": "9.9",
    "HIGH": "10.1",
    "LOW": "9.8",
    "CLOSEP*": "9.9",
    "YCP*": "10",
    "% CHANGE": "-1",
    "TRADE": "279",
    "VALUE (mn)": "5.9060",
    "VOLUME": "594670"
  },
  {
    "#": "317",
    "TRADING CODE": "YPL",
    "LTP*": "24.5",
    "HIGH": "25.3",
    "LOW": "24.4",
    "CLOSEP*": "24.5",
    "YCP*": "24.9",
    "% CHANGE": "-1.61",
    "TRADE": "300",
    "VALUE (mn)": "5.2060",
    "VOLUME": "209875"
  },
  {
    "#": "318",
    "TRADING CODE": "ZAHEENSPIN",
    "LTP*": "5.4",
    "HIGH": "5.5",
    "LOW": "5.4",
    "CLOSEP*": "5.4",
    "YCP*": "5.4",
    "% CHANGE": "0",
    "TRADE": "51",
    "VALUE (mn)": "0.5140",
    "VOLUME": "94281"
  },
  {
    "#": "319",
    "TRADING CODE": "ZEALBANGLA",
    "LTP*": "208.5",
    "HIGH": "222.2",
    "LOW": "203.3",
    "CLOSEP*": "208.5",
    "YCP*": "222.5",
    "% CHANGE": "-6.29",
    "TRADE": "741",
    "VALUE (mn)": "14.6010",
    "VOLUME": "68632"
  },
  {
    "#": "LTP* - Last Traded Price",
    "TRADING CODE": "CLOSEP* -Closing Price",
    "LTP*": "",
    "HIGH": "",
    "LOW": "",
    "CLOSEP*": "",
    "YCP*": "",
    "% CHANGE": "",
    "TRADE": "",
    "VALUE (mn)": "",
    "VOLUME": ""
  },
  {
    "#": "%CHANGE = ((LTP* - YCP)*100/YCP)",
    "TRADING CODE": "YCP* -Yesterday's Closing Price",
    "LTP*": "",
    "HIGH": "",
    "LOW": "",
    "CLOSEP*": "",
    "YCP*": "",
    "% CHANGE": "",
    "TRADE": "",
    "VALUE (mn)": "",
    "VOLUME": ""
  }
]